Workbook

Sheet Control
A1: Model Control Panel
A3: Company Name | B3: #VALUE!
A4: Sector | B4: {=_FV(B3,"Industry")} -> Automobiles & Auto Parts
A5: Scenario | B5: Severe Downside
A6: Forecast Start Year | B6: 2026
A7: Forecast End Year | B7: 2030
A8: Valuation Method | B8: FCFF
A9: Stress Test Toggle | B9: 0
A10: Notes
A12: Scenario Index | B12: =MATCH(B5,{"Base Case","Mild Downside","Severe Downside","Upside"},0) -> 3

Sheet Assumptions
A1: Assumptions
A3: Macroeconomic Inputs
A4: #VALUE! | B4: {=_FV(A4,"Price")/100} -> 0.06633
A5: Equity Risk Premium | B5: 0.0726
A6: Tax Rate | B6: 0.25
A7: Terminal Growth rate | B7: =Stress_Test!L9 -> 0.025
A8: Inflation | B8: 0.04
A10: Capital Market Inputs
A11: Unlevered Beta | B11: 1
A12: Target Debt/(Debt+Equity) | B12: 0.3
A13: Cost of Debt (pre-tax) | B13: 0.085
A15: Other Inputs
A16: Shares Outstanding | B16: {=_FV(Control!B3,"Shares outstanding",TRUE)/10000000} -> 368.2331
A17: Current Market Price | B17: {=_FV(Control!B3,"Price")} -> 363.25

Sheet Revenue_Drivers
A1: Revenue Drivers | B1: FY2023 | C1: FY2024 | D1: FY2025 | E1: FY2026 | F1: FY2027 | G1: FY2028 | H1: FY2029 | I1: FY2030
A3: Volume Growth | B3: =LN(422637/367498) -> 0.13979578 | C3: 0.083 | D3: 0.02 | E3: =AVERAGE(B3:D3) -> 0.080931926 | F3: =AVERAGE(C3:E3) -> 0.061310642 | G3: =AVERAGE(D3:F3) -> 0.054080856 | H3: =AVERAGE(E3:G3) -> 0.065441141 | I3: =AVERAGE(F3:H3) -> 0.060277546
A4: Price Growth | B4: =B5-B3 -> 0.077296019 | C4: =C5-C3 -> 0.14373809 | D4: =D5-D3 -> -0.007000095 | E4: =AVERAGE(B4:D4) -> 0.071344672 | F4: =AVERAGE(C4:E4) -> 0.06936089 | G4: =AVERAGE(D4:F4) -> 0.044568489 | H4: =AVERAGE(E4:G4) -> 0.061758017 | I4: =AVERAGE(F4:H4) -> 0.058562465
A5: Revenue Growth | B5: =LN(B7/278453.62) -> 0.2170918 | C5: =LN(C7/B7) -> 0.22673809 | D5: =LN(D7/C7) -> 0.012999905 | E5: =Stress_Test!L4 -> 0.1522766 | F5: =F3+F4 -> 0.13067153 | G5: =G3+G4 -> 0.098649345 | H5: =H3+H4 -> 0.12719916 | I5: =I3+I4 -> 0.11884001
A7: Revenue | B7: 345966.97 | C7: 434016 | D7: 439695 | E7: =D7*(1+E5) -> 506650.26 | F7: =E7*(1+F5) -> 572855.02 | G7: =F7*(1+G5) -> 629366.8 | H7: =G7*(1+H5) -> 709421.72 | I7: =H7*(1+I5) -> 793729.41

Sheet Operating_Costs
A1: Operating Costs & Margins | B1: FY2023 | C1: FY2024 | D1: FY2025 | E1: FY2026 | F1: FY2027 | G1: FY2028 | H1: FY2029 | I1: FY2030
A3: Revenue | B3: =Revenue_Drivers!B7 -> 345966.97 | C3: =Revenue_Drivers!C7 -> 434016 | D3: =Revenue_Drivers!D7 -> 439695 | E3: =Revenue_Drivers!E7 -> 506650.26 | F3: =Revenue_Drivers!F7 -> 572855.02 | G3: =Revenue_Drivers!G7 -> 629366.8 | H3: =Revenue_Drivers!H7 -> 709421.72 | I3: =Revenue_Drivers!I7 -> 793729.41
A5: COGS as % of Revenue | B5: =B6/B3 -> 0.65459902 | C5: =C6/C3 -> 0.62844619 | D5: =D6/D3 -> 0.61812393 | E5: =AVERAGE(B5:D5) -> 0.63372304 | F5: =AVERAGE(C5:E5) -> 0.62676439 | G5: =AVERAGE(D5:F5) -> 0.62620379 | H5: =AVERAGE(E5:G5) -> 0.62889707 | I5: =AVERAGE(F5:H5) -> 0.62728841
A6: COGS | B6: =208218.05+726.26+22306.95-4781.62 -> 226469.64 | C6: =249277.79+25043.44-1565.53 -> 272755.7 | D6: =241148+27802+2836 -> 271786 | E6: =E3*E5 -> 321075.94 | F6: =F3*F5 -> 359045.13 | G6: =G3*G5 -> 394111.87 | H6: =H3*H5 -> 446153.24 | I6: =I3*I5 -> 497897.26
A8: Employee Cost % of revenue | B8: =B9/B3 -> 0.097277205 | C8: =C9/C3 -> 0.096747585 | D8: =D9/D3 -> 0.10863667 | E8: =AVERAGE(B8:D8) -> 0.10088715 | F8: =AVERAGE(C8:E8) -> 0.10209047 | G8: =AVERAGE(D8:F8) -> 0.10387143 | H8: =AVERAGE(E8:G8) -> 0.10228302 | I8: =AVERAGE(F8:H8) -> 0.10274831
A9: Employee Cost | B9: 33654.7 | C9: 41990 | D9: 47767 | E9: =E3*E8 -> 51114.502 | F9: =F3*F8 -> 58483.038 | G9: =G3*G8 -> 65373.229 | H9: =H3*H8 -> 72561.795 | I9: =I3*I8 -> 81554.352
A11: Other Opex % of revenue | B11: =B12/B3 -> 0.17858919 | C11: =C12/C3 -> 0.17786902 | D11: =D12/D3 -> 0.19422327 | E11: =AVERAGE(B11:D11) -> 0.18356049 | F11: =AVERAGE(C11:E11) -> 0.18521759 | G11: =AVERAGE(D11:F11) -> 0.18766712 | H11: =AVERAGE(E11:G11) -> 0.18548173 | I11: =AVERAGE(F11:H11) -> 0.18612215
A12: Other Opex | B12: 61785.96 | C12: 77198 | D12: 85399 | E12: =E3*E11 -> 93000.97 | F12: =F3*F11 -> 106102.83 | G12: =G3*G11 -> 118111.45 | H12: =H3*H11 -> 131584.77 | I12: =I3*I11 -> 147730.62
A14: EBITDA | B14: =B3-B6-B9-B12 -> 24056.67 | C14: =C3-C6-C9-C12 -> 42072.3 | D14: =D3-D6-D9-D12 -> 34743 | E14: =E3-E6-E9-E12 -> 41458.841 | F14: =F3-F6-F9-F12 -> 49224.03 | G14: =G3-G6-G9-G12 -> 51770.244 | H14: =H3-H6-H9-H12 -> 59121.913 | I14: =I3-I6-I9-I12 -> 66547.172
A15: EBITDA Margin | B15: =B14/B3 -> 0.069534586 | C15: =C14/C3 -> 0.09693721 | D15: =D14/D3 -> 0.079016136 | E15: =Stress_Test!L5 -> 0.081829311 | F15: =F14/F3 -> 0.085927552 | G15: =G14/G3 -> 0.082257666 | H15: =H14/H3 -> 0.083338176 | I15: =I14/I3 -> 0.083841132
A17: Depreciation | B17: 24860.36 | C17: 27270.13 | D17: 23256 | E17: 0 | F17: 0 | G17: 0 | H17: 0 | I17: 0
A18: EBIT | B18: =B14-B17 -> -803.69 | C18: =C14-C17 -> 14802.17 | D18: =D14-D17 -> 11487 | E18: =E14-E17 -> 41458.841 | F18: =F14-F17 -> 49224.03 | G18: =G14-G17 -> 51770.244 | H18: =H14-H17 -> 59121.913 | I18: =I14-I17 -> 66547.172

Sheet Working_Capital
A1: Working Capital | B1: FY2023 | C1: FY2024 | D1: FY2025 | E1: FY2026 | F1: FY2027 | G1: FY2028 | H1: FY2029 | I1: FY2030
A3: Revenue | B3: =Operating_Costs!B3 -> 345966.97 | C3: =Operating_Costs!C3 -> 434016 | D3: =Operating_Costs!D3 -> 439695 | E3: =Operating_Costs!E3 -> 506650.26 | F3: =Operating_Costs!F3 -> 572855.02 | G3: =Operating_Costs!G3 -> 629366.8 | H3: =Operating_Costs!H3 -> 709421.72 | I3: =Operating_Costs!I3 -> 793729.41
A4: COGS | B4: =Operating_Costs!B6 -> 226469.64 | C4: =Operating_Costs!C6 -> 272755.7 | D4: =Operating_Costs!D6 -> 271786 | E4: =Operating_Costs!E6 -> 321075.94 | F4: =Operating_Costs!F6 -> 359045.13 | G4: =Operating_Costs!G6 -> 394111.87 | H4: =Operating_Costs!H6 -> 446153.24 | I4: =Operating_Costs!I6 -> 497897.26
A6: AR Days | B6: =(B7/B3)*365 -> 16.603779 | C6: =(C7/C3)*365 -> 14.256181 | D6: =(D7/D3)*365 -> 10.997441 | E6: =D6 -> 10.997441 | F6: =E6 -> 10.997441 | G6: =F6 -> 10.997441 | H6: =G6 -> 10.997441 | I6: =H6 -> 10.997441
A7: Accounts Receivable | B7: 15737.97 | C7: 16951.81 | D7: 13248 | E7: =E3*E6/365 -> 15265.36 | F7: =F3*F6/365 -> 17260.108 | G7: =G3*G6/365 -> 18962.807 | H7: =H3*H6/365 -> 21374.86 | I7: =I3*I6/365 -> 23915.048
A9: Inventory Days | B9: =(B10/B4)*365 -> 65.685261 | C9: =(C10/C4)*365 -> 63.949996 | D9: =(D10/D4)*365 -> 63.480772 | E9: =Stress_Test!L7 -> 63.480772 | F9: =E9 -> 63.480772 | G9: =F9 -> 63.480772 | H9: =G9 -> 63.480772 | I9: =H9 -> 63.480772
A10: Inventory | B10: 40755.39 | C10: 47788.29 | D10: 47269 | E10: =D4*E9/365 -> 47269 | F10: =E4*F9/365 -> 55841.503 | G10: =F4*G9/365 -> 62445.101 | H10: =G4*H9/365 -> 68543.906 | I10: =H4*I9/365 -> 77594.938
A12: AP Days | B12: =(B13/B4)*365 -> 116.13193 | C12: =(C13/C4)*365 -> 117.81853 | D12: =(D13/D4)*365 -> 126.34378 | E12: =D12 -> 126.34378 | F12: =E12 -> 126.34378 | G12: =F12 -> 126.34378 | H12: =G12 -> 126.34378 | I12: =H12 -> 126.34378
A13: Accounts Payable | B13: =316.01+71739.76 -> 72055.77 | C13: =502.31+87540.64 -> 88042.95 | D13: =452+93626 -> 94078 | E13: =E4*E12/365 -> 111139.58 | F13: =F4*F12/365 -> 124282.51 | G13: =G4*G12/365 -> 136420.77 | H13: =H4*H12/365 -> 154434.76 | I13: =I4*I12/365 -> 172345.81
A15: Net Working Capital | B15: =B7+B10-B13 -> -15562.41 | C15: =C7+C10-C13 -> -23302.85 | D15: =D7+D10-D13 -> -33561 | E15: =E7+E10-E13 -> -48605.223 | F15: =F7+F10-F13 -> -51180.903 | G15: =G7+G10-G13 -> -55012.867 | H15: =H7+H10-H13 -> -64515.992 | I15: =I7+I10-I13 -> -70835.825
A16: WC % of Revenue | B16: =B15/B3 -> -0.044982358 | C16: =C15/C3 -> -0.053691223 | D16: =D15/D3 -> -0.076327909 | E16: =AVERAGE($B$16:$D$16) -> -0.05833383 | F16: =AVERAGE($B$16:$D$16) -> -0.05833383 | G16: =AVERAGE($B$16:$D$16) -> -0.05833383 | H16: =AVERAGE($B$16:$D$16) -> -0.05833383 | I16: =AVERAGE($B$16:$D$16) -> -0.05833383
A17: Change in WC | B17: 0 | C17: =C15-B15 -> -7740.44 | D17: =D15-C15 -> -10258.15 | E17: =E15-D15 -> -15044.223 | F17: =F15-E15 -> -2575.6801 | G17: =G15-F15 -> -3831.9642 | H17: =H15-G15 -> -9503.1247 | I17: =I15-H15 -> -6319.8337
A19: WC | E19: =E3*E16 -> -29554.85 | F19: =F3*F16 -> -33416.828 | G19: =G3*G16 -> -36713.376 | H19: =H3*H16 -> -41383.286 | I19: =I3*I16 -> -46301.276
A20: Change in WC | E20: =D16*(E3-D3) -> -5110.5549 | F20: =E16*(F3-E3) -> -3861.9775 | G20: =F16*(G3-F3) -> -3296.5482 | H20: =G16*(H3-G3) -> -4669.9105 | I20: =H16*(I3-H3) -> -4917.9902

Sheet Capex_Depreciation
A1: Capex & Depreciation | B1: FY2023 | C1: FY2024 | D1: FY2025 | E1: FY2026 | F1: FY2027 | G1: FY2028 | H1: FY2029 | I1: FY2030
A3: Revenue | B3: =Working_Capital!B3 -> 345966.97 | C3: =Working_Capital!C3 -> 434016 | D3: =Working_Capital!D3 -> 439695 | E3: =Working_Capital!E3 -> 506650.26 | F3: =Working_Capital!F3 -> 572855.02 | G3: =Working_Capital!G3 -> 629366.8 | H3: =Working_Capital!H3 -> 709421.72 | I3: =Working_Capital!I3 -> 793729.41
A5: Capex % of Revenue | B5: =B6/B3 -> 0.024547517 | C5: =C6/C3 -> 0.029894612 | D5: =D6/D3 -> 0.0345444 | E5: =Stress_Test!L6 -> 0.029662176 | F5: =AVERAGE(C5:E5) -> 0.031367063 | G5: =AVERAGE(D5:F5) -> 0.03185788 | H5: =AVERAGE(E5:G5) -> 0.030962373 | I5: =AVERAGE(F5:H5) -> 0.031395772
A6: Capex | B6: 8492.63 | C6: 12974.74 | D6: 15189 | E6: =E3*E5 -> 15028.349 | F6: =F3*F5 -> 17968.78 | G6: =G3*G5 -> 20050.292 | H6: =H3*H5 -> 21965.38 | I6: =I3*I5 -> 24919.747
A8: Opening PP&E | B8: 80900.13 | C8: 76641.43 | D8: 73124.66 | E8: =D12 -> 65057.66 | F8: =E12 -> 58809.04 | G8: =F12 -> 57157.269 | H8: =G12 -> 58560.732 | I8: =H12 -> 61261.259
A9: Depreciation % of Opening PP&E | B9: =B10/B8 -> 0.30729691 | C9: =C10/C8 -> 0.35581447 | D9: =D10/D8 -> 0.31803225 | E9: =AVERAGE(B9:D9) -> 0.32704788 | F9: =AVERAGE(C9:E9) -> 0.33363153 | G9: =AVERAGE(D9:F9) -> 0.32623722 | H9: =AVERAGE(E9:G9) -> 0.32897221 | I9: =AVERAGE(F9:H9) -> 0.32961365
A10: Depreciation | B10: =Operating_Costs!B17 -> 24860.36 | C10: =Operating_Costs!C17 -> 27270.13 | D10: =Operating_Costs!D17 -> 23256 | E10: =E8*E9 -> 21276.97 | F10: =F8*F9 -> 19620.55 | G10: =G8*G9 -> 18646.829 | H10: =H8*H9 -> 19264.854 | I10: =I8*I9 -> 20192.547
A12: Closing PP&E | B12: =B8+B6-B10 -> 64532.4 | C12: =C8+C6-C10 -> 62346.04 | D12: =D8+D6-D10 -> 65057.66 | E12: =E8+E6-E10 -> 58809.04 | F12: =F8+F6-F10 -> 57157.269 | G12: =G8+G6-G10 -> 58560.732 | H12: =H8+H6-H10 -> 61261.259 | I12: =I8+I6-I10 -> 65988.459

Sheet Debt_Interest
A1: Debt & Interest | B1: FY2023 | C1: FY2024 | D1: FY2025 | E1: FY2026 | F1: FY2027 | G1: FY2028 | H1: FY2029 | I1: FY2030
A3: Opening Debt | B3: =97759.17+41917.87 -> 139677.04 | C3: =88695.81+36964.66 -> 125660.47 | D3: =62148.53+36351.56 -> 98500.09 | E3: =D6 -> 72991.88 | F3: =E6 -> 72991.88 | G3: =F6 -> 72991.88 | H3: =G6 -> 72991.88 | I3: =H6 -> 72991.88
A4: New Borrowings | B4: =31308.62+16866.24 -> 48174.86 | C4: =16315.06+28125.45 -> 44440.51 | D4: =11629.4+10194.1 -> 21823.5
A5: Repayments | B5: =23355.8+19460.45 -> 42816.25 | C5: =31559.46+30997.82 -> 62557.28 | D5: =31675.2+15656.51 -> 47331.71
A6: Closing Debt | B6: =B3+B4-B5 -> 145035.65 | C6: =C3+C4-C5 -> 107543.7 | D6: =D3+D4-D5 -> 72991.88 | E6: =E3+E4-E5 -> 72991.88 | F6: =F3+F4-F5 -> 72991.88 | G6: =G3+G4-G5 -> 72991.88 | H6: =H3+H4-H5 -> 72991.88 | I6: =I3+I4-I5 -> 72991.88
A8: Average Debt | B8: =AVERAGE(B3,B6) -> 142356.35 | C8: =AVERAGE(C3,C6) -> 116602.09 | D8: =AVERAGE(D3,D6) -> 85745.985 | E8: =AVERAGE(E3,E6) -> 72991.88 | F8: =AVERAGE(F3,F6) -> 72991.88 | G8: =AVERAGE(G3,G6) -> 72991.88 | H8: =AVERAGE(H3,H6) -> 72991.88 | I8: =AVERAGE(I3,I6) -> 72991.88
A9: Cost of Debt | B9: =B10/B8 -> 0.071830167 | C9: =C10/C8 -> 0.06512748 | D9: =D10/D8 -> 0.059279744 | E9: =Assumptions!$B$13 -> 0.085 | F9: =Assumptions!$B$13 -> 0.085 | G9: =Assumptions!$B$13 -> 0.085 | H9: =Assumptions!$B$13 -> 0.085 | I9: =Assumptions!$B$13 -> 0.085
A10: Interest Expense | B10: 10225.48 | C10: 7594 | D10: 5083 | E10: =E8*E9 -> 6204.3098 | F10: =F8*F9 -> 6204.3098 | G10: =G8*G9 -> 6204.3098 | H10: =H8*H9 -> 6204.3098 | I10: =I8*I9 -> 6204.3098

Sheet Income_Statement
A1: Income Statement | B1: FY2023 | C1: FY2024 | D1: FY2025 | E1: FY2026 | F1: FY2027 | G1: FY2028 | H1: FY2029 | I1: FY2030
A3: Revenue | B3: =Revenue_Drivers!B7 -> 345966.97 | C3: =Revenue_Drivers!C7 -> 434016 | D3: =Revenue_Drivers!D7 -> 439695 | E3: =Revenue_Drivers!E7 -> 506650.26 | F3: =Revenue_Drivers!F7 -> 572855.02 | G3: =Revenue_Drivers!G7 -> 629366.8 | H3: =Revenue_Drivers!H7 -> 709421.72 | I3: =Revenue_Drivers!I7 -> 793729.41
A4: COGS | B4: =Working_Capital!B4 -> 226469.64 | C4: =Working_Capital!C4 -> 272755.7 | D4: =Working_Capital!D4 -> 271786 | E4: =Working_Capital!E4 -> 321075.94 | F4: =Working_Capital!F4 -> 359045.13 | G4: =Working_Capital!G4 -> 394111.87 | H4: =Working_Capital!H4 -> 446153.24 | I4: =Working_Capital!I4 -> 497897.26
A5: Gross Profit | B5: =B3-B4 -> 119497.33 | C5: =C3-C4 -> 161260.3 | D5: =D3-D4 -> 167909 | E5: =E3-E4 -> 185574.31 | F5: =F3-F4 -> 213809.9 | G5: =G3-G4 -> 235254.93 | H5: =H3-H4 -> 263268.48 | I5: =I3-I4 -> 295832.15
A7: Employee Cost | B7: =Operating_Costs!B9 -> 33654.7 | C7: =Operating_Costs!C9 -> 41990 | D7: =Operating_Costs!D9 -> 47767 | E7: =Operating_Costs!E9 -> 51114.502 | F7: =Operating_Costs!F9 -> 58483.038 | G7: =Operating_Costs!G9 -> 65373.229 | H7: =Operating_Costs!H9 -> 72561.795 | I7: =Operating_Costs!I9 -> 81554.352
A8: Other Opex | B8: =Operating_Costs!B12 -> 61785.96 | C8: =Operating_Costs!C12 -> 77198 | D8: =Operating_Costs!D12 -> 85399 | E8: =Operating_Costs!E12 -> 93000.97 | F8: =Operating_Costs!F12 -> 106102.83 | G8: =Operating_Costs!G12 -> 118111.45 | H8: =Operating_Costs!H12 -> 131584.77 | I8: =Operating_Costs!I12 -> 147730.62
A10: EBITDA | B10: =Operating_Costs!B14 -> 24056.67 | C10: =Operating_Costs!C14 -> 42072.3 | D10: =Operating_Costs!D14 -> 34743 | E10: =Operating_Costs!E14 -> 41458.841 | F10: =Operating_Costs!F14 -> 49224.03 | G10: =Operating_Costs!G14 -> 51770.244 | H10: =Operating_Costs!H14 -> 59121.913 | I10: =Operating_Costs!I14 -> 66547.172
A12: Depreciation | B12: =Capex_Depreciation!B10 -> 24860.36 | C12: =Capex_Depreciation!C10 -> 27270.13 | D12: =Capex_Depreciation!D10 -> 23256 | E12: =Capex_Depreciation!E10 -> 21276.97 | F12: =Capex_Depreciation!F10 -> 19620.55 | G12: =Capex_Depreciation!G10 -> 18646.829 | H12: =Capex_Depreciation!H10 -> 19264.854 | I12: =Capex_Depreciation!I10 -> 20192.547
A13: EBIT | B13: =B10-B12 -> -803.69 | C13: =C10-C12 -> 14802.17 | D13: =D10-D12 -> 11487 | E13: =E10-E12 -> 20181.872 | F13: =F10-F12 -> 29603.48 | G13: =G10-G12 -> 33123.415 | H13: =H10-H12 -> 39857.059 | I13: =I10-I12 -> 46354.625
A15: Interest | B15: =Debt_Interest!B10 -> 10225.48 | C15: =Debt_Interest!C10 -> 7594 | D15: =Debt_Interest!D10 -> 5083 | E15: =Debt_Interest!E10 -> 6204.3098 | F15: =Debt_Interest!F10 -> 6204.3098 | G15: =Debt_Interest!G10 -> 6204.3098 | H15: =Debt_Interest!H10 -> 6204.3098 | I15: =Debt_Interest!I10 -> 6204.3098
A16: EBT | B16: =B13-B15 -> -11029.17 | C16: =C13-C15 -> 7208.17 | D16: =D13-D15 -> 6404 | E16: =E13-E15 -> 13977.562 | F16: =F13-F15 -> 23399.17 | G16: =G13-G15 -> 26919.106 | H16: =H13-H15 -> 33652.749 | I16: =I13-I15 -> 40150.315
A18: Tax | B18: 0 | C18: =C16*(1-Assumptions!$B$6) -> 5406.1275 | D18: =D16*(1-Assumptions!$B$6) -> 4803 | E18: =E16*(1-Assumptions!$B$6) -> 10483.172 | F18: =F16*(1-Assumptions!$B$6) -> 17549.378 | G18: =G16*(1-Assumptions!$B$6) -> 20189.329 | H18: =H16*(1-Assumptions!$B$6) -> 25239.562 | I18: =I16*(1-Assumptions!$B$6) -> 30112.736
A19: Net Income | B19: =B16-B18 -> -11029.17 | C19: =C16-C18 -> 1802.0425 | D19: =D16-D18 -> 1601 | E19: =E16-E18 -> 3494.3905 | F19: =F16-F18 -> 5849.7925 | G19: =G16-G18 -> 6729.7764 | H19: =H16-H18 -> 8413.1873 | I19: =I16-I18 -> 10037.579

Sheet Balance_Sheet
A1: Balance Sheet | B1: FY2023 | C1: FY2024 | D1: FY2025 | E1: FY2026 | F1: FY2027 | G1: FY2028 | H1: FY2029 | I1: FY2030
A3: Cash | B3: =31886.95+5128.61 -> 37015.56 | C3: =40014.76+5791.93 -> 45806.69 | D3: =34349+6485 -> 40834 | E3: =Cash_Flow!E17 -> 79802.795 | F3: =Cash_Flow!F17 -> 119379.94 | G3: =Cash_Flow!G17 -> 161510.29 | H3: =Cash_Flow!H17 -> 206483.8 | I3: =Cash_Flow!I17 -> 256715.68
A4: Accounts Receivable | B4: =Working_Capital!B7 -> 15737.97 | C4: =Working_Capital!C7 -> 16951.81 | D4: =Working_Capital!D7 -> 13248 | E4: =Working_Capital!E7 -> 15265.36 | F4: =Working_Capital!F7 -> 17260.108 | G4: =Working_Capital!G7 -> 18962.807 | H4: =Working_Capital!H7 -> 21374.86 | I4: =Working_Capital!I7 -> 23915.048
A5: Inventory | B5: =Working_Capital!B10 -> 40755.39 | C5: =Working_Capital!C10 -> 47788.29 | D5: =Working_Capital!D10 -> 47269 | E5: =Working_Capital!E10 -> 47269 | F5: =Working_Capital!F10 -> 55841.503 | G5: =Working_Capital!G10 -> 62445.101 | H5: =Working_Capital!H10 -> 68543.906 | I5: =Working_Capital!I10 -> 77594.938
A6: Other Current Assets | B6: 9587.33 | C6: 10429.38 | D6: 11794 | E6: =D6 -> 11794 | F6: =E6 -> 11794 | G6: =F6 -> 11794 | H6: =G6 -> 11794 | I6: =H6 -> 11794
A7: Total Current Assets | B7: =B3+B4+B5+B6 -> 103096.25 | C7: =C3+C4+C5+C6 -> 120976.17 | D7: =D3+D4+D5+D6 -> 113145 | E7: =E3+E4+E5+E6 -> 154131.15 | F7: =F3+F4+F5+F6 -> 204275.55 | G7: =G3+G4+G5+G6 -> 254712.2 | H7: =H3+H4+H5+H6 -> 308196.56 | I7: =I3+I4+I5+I6 -> 370019.67
A9: PP&E | B9: =Capex_Depreciation!B12 -> 64532.4 | C9: =Capex_Depreciation!C12 -> 62346.04 | D9: =Capex_Depreciation!D12 -> 65057.66 | E9: =Capex_Depreciation!E12 -> 58809.04 | F9: =Capex_Depreciation!F12 -> 57157.269 | G9: =Capex_Depreciation!G12 -> 58560.732 | H9: =Capex_Depreciation!H12 -> 61261.259 | I9: =Capex_Depreciation!I12 -> 65988.459
A10: Other Assets | B10: 8602.05 | C10: 5720.44 | D10: 6852 | E10: =D10 -> 6852 | F10: =E10 -> 6852 | G10: =F10 -> 6852 | H10: =G10 -> 6852 | I10: =H10 -> 6852
A11: Total Assets | B11: =B9+B10+B7 -> 176230.7 | C11: =C9+C10+C7 -> 189042.65 | D11: =D9+D10+D7 -> 185054.66 | E11: =E9+E10+E7 -> 219792.19 | F11: =F9+F10+F7 -> 268284.82 | G11: =G9+G10+G7 -> 320124.93 | H11: =H9+H10+H7 -> 376309.82 | I11: =I9+I10+I7 -> 442860.13
A13: Accounts Payable | B13: =Working_Capital!B13 -> 72055.77 | C13: =Working_Capital!C13 -> 88042.95 | D13: =Working_Capital!D13 -> 94078 | E13: =Working_Capital!E13 -> 111139.58 | F13: =Working_Capital!F13 -> 124282.51 | G13: =Working_Capital!G13 -> 136420.77 | H13: =Working_Capital!H13 -> 154434.76 | I13: =Working_Capital!I13 -> 172345.81
A14: Other Current Liabilities | B14: 11033 | C14: 12990.3 | D14: 13340 | E14: =D14 -> 13340 | F14: =E14 -> 13340 | G14: =F14 -> 13340 | H14: =G14 -> 13340 | I14: =H14 -> 13340
A15: Total Current Liabilities | B15: =B13+B14 -> 83088.77 | C15: =C13+C14 -> 101033.25 | D15: =D13+D14 -> 107418 | E15: =E13+E14 -> 124479.58 | F15: =F13+F14 -> 137622.51 | G15: =G13+G14 -> 149760.77 | H15: =H13+H14 -> 167774.76 | I15: =I13+I14 -> 185685.81
A17: Debt (BL Fig-26 onw) | B17: =Debt_Interest!B6 -> 145035.65 | C17: =Debt_Interest!C6 -> 107543.7 | D17: =Debt_Interest!D6 -> 72991.88 | E17: =E11-SUM(E13:E14,E18,E21:E22) -> 67273.489 | F17: =F11-SUM(F13:F14,F18,F21:F22) -> 96776.617 | G17: =G11-SUM(G13:G14,G18,G21:G22) -> 129753.32 | H17: =H11-SUM(H13:H14,H18,H21:H22) -> 159506.88 | I17: =I11-SUM(I13:I14,I18,I21:I22) -> 198109.78
A18: Other Liabilities | B18: 9264.29 | C18: 12234 | D18: 15376 | E18: =D18 -> 15376 | F18: =E18 -> 15376 | G18: =F18 -> 15376 | H18: =G18 -> 15376 | I18: =H18 -> 15376
A19: Total Liabilities | B19: =B15+B17+B18 -> 237388.71 | C19: =C15+C17+C18 -> 220810.95 | D19: =D15+D17+D18 -> 195785.88 | E19: =E15+E17+E18 -> 207129.07 | F19: =F15+F17+F18 -> 249775.13 | G19: =G15+G17+G18 -> 294890.09 | H19: =H15+H17+H18 -> 342657.64 | I19: =I15+I17+I18 -> 399171.59
A21: Share Capital | B21: 766.02 | C21: 767 | D21: 736 | E21: =AVERAGE(B21:D21) -> 756.34 | F21: =AVERAGE(C21:E21) -> 753.11333 | G21: =AVERAGE(D21:F21) -> 748.48444 | H21: =AVERAGE(E21:G21) -> 752.64593 | I21: =AVERAGE(F21:H21) -> 751.41457
A22: Retained Earnings | B22: 5009.35 | C22: =B22+Income_Statement!C19 -> 6811.3925 | D22: =C22+Income_Statement!D19 -> 8412.3925 | E22: =D22+Income_Statement!E19 -> 11906.783 | F22: =E22+Income_Statement!F19 -> 17756.576 | G22: =F22+Income_Statement!G19 -> 24486.352 | H22: =G22+Income_Statement!H19 -> 32899.539 | I22: =H22+Income_Statement!I19 -> 42937.118
A23: Total Equity | B23: =B21+B22 -> 5775.37 | C23: =C21+C22 -> 7578.3925 | D23: =D21+D22 -> 9148.3925 | E23: =E21+E22 -> 12663.123 | F23: =F21+F22 -> 18509.689 | G23: =G21+G22 -> 25234.836 | H23: =H21+H22 -> 33652.185 | I23: =I21+I22 -> 43688.533
A25: Total Liabilities & Equity | B25: =B19+B23 -> 243164.08 | C25: =C19+C23 -> 228389.34 | D25: =D19+D23 -> 204934.27 | E25: =E19+E23 -> 219792.19 | F25: =F19+F23 -> 268284.82 | G25: =G19+G23 -> 320124.93 | H25: =H19+H23 -> 376309.82 | I25: =I19+I23 -> 442860.13

Sheet Cash_Flow
A1: Cash Flow Statement | B1: FY2023 | C1: FY2024 | D1: FY2025 | E1: FY2026 | F1: FY2027 | G1: FY2028 | H1: FY2029 | I1: FY2030
A3: Net Income | B3: =Income_Statement!B19 -> -11029.17 | C3: =Income_Statement!C19 -> 1802.0425 | D3: =Income_Statement!D19 -> 1601 | E3: =Income_Statement!E19 -> 3494.3905 | F3: =Income_Statement!F19 -> 5849.7925 | G3: =Income_Statement!G19 -> 6729.7764 | H3: =Income_Statement!H19 -> 8413.1873 | I3: =Income_Statement!I19 -> 10037.579
A4: Depreciation | B4: =Income_Statement!B12 -> 24860.36 | C4: =Income_Statement!C12 -> 27270.13 | D4: =Income_Statement!D12 -> 23256 | E4: =Income_Statement!E12 -> 21276.97 | F4: =Income_Statement!F12 -> 19620.55 | G4: =Income_Statement!G12 -> 18646.829 | H4: =Income_Statement!H12 -> 19264.854 | I4: =Income_Statement!I12 -> 20192.547
A5: Change in WC | B5: =Working_Capital!B17 -> 0 | C5: =Working_Capital!C17 -> -7740.44 | D5: =Working_Capital!D17 -> -10258.15 | E5: =Working_Capital!E20 -> -5110.5549 | F5: =Working_Capital!F20 -> -3861.9775 | G5: =Working_Capital!G20 -> -3296.5482 | H5: =Working_Capital!H20 -> -4669.9105 | I5: =Working_Capital!I20 -> -4917.9902
A6: Cash from Operations | B6: =B3+B4+B5 -> 13831.19 | C6: =C3+C4+C5 -> 21331.733 | D6: =D3+D4+D5 -> 14598.85 | E6: =E3+E4+E5 -> 19660.805 | F6: =F3+F4+F5 -> 21608.365 | G6: =G3+G4+G5 -> 22080.057 | H6: =H3+H4+H5 -> 23008.13 | I6: =I3+I4+I5 -> 25312.136
A8: Capex | B8: =Capex_Depreciation!B6 -> 8492.63 | C8: =Capex_Depreciation!C6 -> 12974.74 | D8: =Capex_Depreciation!D6 -> 15189 | E8: =Capex_Depreciation!E6 -> 15028.349 | F8: =Capex_Depreciation!F6 -> 17968.78 | G8: =Capex_Depreciation!G6 -> 20050.292 | H8: =Capex_Depreciation!H6 -> 21965.38 | I8: =Capex_Depreciation!I6 -> 24919.747
A9: Cash from Investing | B9: =B8 -> 8492.63 | C9: =C8 -> 12974.74 | D9: =D8 -> 15189 | E9: =E8 -> 15028.349 | F9: =F8 -> 17968.78 | G9: =G8 -> 20050.292 | H9: =H8 -> 21965.38 | I9: =I8 -> 24919.747
A11: New Borrowings | B11: =Debt_Interest!B4 -> 48174.86 | C11: =Debt_Interest!C4 -> 44440.51 | D11: =Debt_Interest!D4 -> 21823.5 | E11: =Debt_Interest!E4 -> 0 | F11: =Debt_Interest!F4 -> 0 | G11: =Debt_Interest!G4 -> 0 | H11: =Debt_Interest!H4 -> 0 | I11: =Debt_Interest!I4 -> 0
A12: Repayments | B12: =Debt_Interest!B5 -> 42816.25 | C12: =Debt_Interest!C5 -> 62557.28 | D12: =Debt_Interest!D5 -> 47331.71 | E12: =Debt_Interest!E5 -> 0 | F12: =Debt_Interest!F5 -> 0 | G12: =Debt_Interest!G5 -> 0 | H12: =Debt_Interest!H5 -> 0 | I12: =Debt_Interest!I5 -> 0
A13: Cash from Financing | B13: =B11-B12 -> 5358.61 | C13: =C11-C12 -> -18116.77 | D13: =D11-D12 -> -25508.21 | E13: =E11-E12 -> 0 | F13: =F11-F12 -> 0 | G13: =G11-G12 -> 0 | H13: =H11-H12 -> 0 | I13: =I11-I12 -> 0
A15: Net Change in Cash | B15: =B6+B9+B13 -> 27682.43 | C15: =C6+C9+C13 -> 16189.703 | D15: =D6+D9+D13 -> 4279.64 | E15: =E6+E9+E13 -> 34689.155 | F15: =F6+F9+F13 -> 39577.145 | G15: =G6+G9+G13 -> 42130.349 | H15: =H6+H9+H13 -> 44973.51 | I15: =I6+I9+I13 -> 50231.883
A16: Opening Cash | B16: =Balance_Sheet!B3 -> 37015.56 | C16: =Balance_Sheet!C3 -> 45806.69 | D16: =Balance_Sheet!D3 -> 40834 | E16: =D17 -> 45113.64 | F16: =E17 -> 79802.795 | G16: =F17 -> 119379.94 | H16: =G17 -> 161510.29 | I16: =H17 -> 206483.8
A17: Closing Cash | B17: =B15+B16 -> 64697.99 | C17: =C15+C16 -> 61996.393 | D17: =D15+D16 -> 45113.64 | E17: =E15+E16 -> 79802.795 | F17: =F15+F16 -> 119379.94 | G17: =G15+G16 -> 161510.29 | H17: =H15+H16 -> 206483.8 | I17: =I15+I16 -> 256715.68

Sheet WACC
A1: WACC Calculation
A3: Risk-free rate | B3: =Assumptions!B4 -> 0.06633
A4: Equity Risk Premium | B4: =Assumptions!B5 -> 0.0726
A5: Levered Beta | B5: {=_FV(Control!B3,"Beta")} -> 1.0739
A6: Cost of Equity | B6: =(B3+B5)*B4 -> 0.082780698
A8: Cost of Debt (pre-tax) | B8: =Assumptions!B13 -> 0.085
A9: Tax rate | B9: =Assumptions!B6 -> 0.25
A10: After-tax Cost of Debt | B10: =B8*(1-B9) -> 0.06375
A12: Shares Outstanding | B12: =Assumptions!B16 -> 368.2331
A13: Current Market Price | B13: =Assumptions!B17 -> 363.25
A14: Market Value of Equity | B14: =B12*B13 -> 133760.67
A15: Net Debt | B15: =Balance_Sheet!D17-Balance_Sheet!D3 -> 32157.88
A16: Total Capital | B16: =B14+B15 -> 165918.55
A17: Weight of Equity | B17: =B14/$B$16 -> 0.80618274
A18: Weight of Debt | B18: =B15/$B$16 -> 0.19381726
A20: WACC | B20: =Stress_Test!L8 -> 0.079225061
A21: WACC_1 | B21: 0.079225061

Sheet DCF_Valuation
A1: DCF Valuation | B1: FY2026 | C1: FY2027 | D1: FY2028 | E1: FY2029 | F1: FY2030
A3: EBIT | B3: =Income_Statement!E13 -> 20181.872 | C3: =Income_Statement!F13 -> 29603.48 | D3: =Income_Statement!G13 -> 33123.415 | E3: =Income_Statement!H13 -> 39857.059 | F3: =Income_Statement!I13 -> 46354.625
A4: NOPAT | B4: =B3*(1-Assumptions!$B$6) -> 15136.404 | C4: =C3*(1-Assumptions!$B$6) -> 22202.61 | D4: =D3*(1-Assumptions!$B$6) -> 24842.562 | E4: =E3*(1-Assumptions!$B$6) -> 29892.794 | F4: =F3*(1-Assumptions!$B$6) -> 34765.968
A5: Depreciation | B5: =Income_Statement!E12 -> 21276.97 | C5: =Income_Statement!F12 -> 19620.55 | D5: =Income_Statement!G12 -> 18646.829 | E5: =Income_Statement!H12 -> 19264.854 | F5: =Income_Statement!I12 -> 20192.547
A6: Capex | B6: =Cash_Flow!E8 -> 15028.349 | C6: =Cash_Flow!F8 -> 17968.78 | D6: =Cash_Flow!G8 -> 20050.292 | E6: =Cash_Flow!H8 -> 21965.38 | F6: =Cash_Flow!I8 -> 24919.747
A7: Change in WC | B7: =Cash_Flow!E5 -> -5110.5549 | C7: =Cash_Flow!F5 -> -3861.9775 | D7: =Cash_Flow!G5 -> -3296.5482 | E7: =Cash_Flow!H5 -> -4669.9105 | F7: =Cash_Flow!I5 -> -4917.9902
A8: FCFF | B8: =B4+B5-B6-B7 -> 26495.579 | C8: =C4+C5-C6-C7 -> 27716.358 | D8: =D4+D5-D6-D7 -> 26735.647 | E8: =E4+E5-E6-E7 -> 31862.178 | F8: =F4+F5-F6-F7 -> 34956.758
A11: WACC | B11: =WACC!B20 -> 0.079225061
A12: Discount Factor | B12: =1/(1+B11)^5 -> 0.68303018
A13: PV of FCFF | B13: =NPV(Sensitivity!I4,B8:F8) -> 116979.89
A15: Terminal Growth | B15: =Assumptions!B7 -> 0.025
A16: Terminal Value | B16: =F8*(1+Sensitivity!I5)/(Sensitivity!I4-Sensitivity!I5) -> 660777.08
A17: PV of Terminal Value | B17: =B16*B12 -> 451330.69
A19: Enterprise Value | B19: =B13+B17 -> 568310.58
A20: Net Debt | B20: =WACC!B15 -> 32157.88
A21: Equity Value | B21: =B19-B20 -> 536152.7
A22: Shares Outstanding | B22: =WACC!B12 -> 368.2331
A23: Intrinsic Value | B23: =B21/B22 -> 1456.0144
A24: CMP | B24: =WACC!B13 -> 363.25
A25: Upside/Downside | B25: =(B23-B24)/B24 -> 3.0082984

Sheet Sensitivity
A1: Intrinsic Value Sensitivity
A3: =DCF_Valuation!B23 -> 1456.0144 | B3: 0.025 | C3: 0.03 | D3: 0.035 | E3: 0.04 | F3: 0.045
A4: 0.085 | B4: 1333.0325 | C4: 1439.6268 | D4: 1567.54 | E4: 1723.8783 | F4: 1919.3012 | H4: WACC input | I4: =DCF_Valuation!B11 -> 0.079225061
A5: 0.09 | B5: 1243.5844 | C5: 1334.1953 | D5: 1441.2808 | E5: 1569.7834 | F5: 1726.8422 | H5: g input | I5: =Assumptions!B7 -> 0.025
A6: 0.095 | B6: 1166.3985 | C6: 1244.4212 | D6: 1335.4477 | E6: 1443.0245 | F6: 1572.1166
A7: 0.1 | B7: 1099.0379 | C7: 1166.9663 | D7: 1245.3453 | E7: 1336.7874 | F7: 1444.8554 | I7: Optimistic
A8: 0.105 | B8: 1039.6742 | C8: 1099.3818 | D8: 1167.619 | E8: 1246.3542 | F8: 1338.212 | I8: Conservative
A9: 0.11 | B9: 986.90909 | C9: 1039.8306 | D9: 1099.8083 | E9: 1168.3543 | F9: 1247.4458

Sheet Stress_Test
A1: Stress Test-Key Assumptions
A3: Scenario | B3: Revenue Growth | C3: EBITDA Margin | D3: Capex % of Revenue | E3: Inventory Days | F3: WACC | G3: Terminal g | H3: Intrinsic Value | I3: Upside/Downside | K3: Driver | L3: Helper Value
A4: Base Case | B4: 0.1522766 | C4: 0.081829311 | D4: 0.029662176 | E4: 63.480772 | F4: 0.079225061 | G4: 0.025 | H4: =DCF_Valuation!B23 -> 1456.0144 | I4: =(H4/DCF_Valuation!$B$24)-1 -> 3.0082984 | K4: Rev Growth | L4: 0.1522766
A5: Mild Downside | B5: 0.1322766 | C5: 0.071829311 | D5: 0.039662176 | E5: 68.480772 | F5: 0.089225061 | G5: 0.02 | H5: 1004.68 | I5: =(H5/DCF_Valuation!$B$24)-1 -> 1.7658087 | K5: EBITDA Margin | L5: 0.081829311
A6: Severe Downside | B6: 0.1022766 | C6: 0.051829311 | D6: 0.049662176 | E6: 73.480772 | F6: 0.099225061 | G6: 0.015 | H6: 704.68 | I6: =(H6/DCF_Valuation!$B$24)-1 -> 0.93993118 | K6: Capex % | L6: 0.029662176
A7: Upside | B7: 0.1822766 | C7: 0.096829311 | D7: 0.019662176 | E7: 58.480772 | F7: 0.071725061 | G7: 0.03 | H7: 2124.19 | I7: =(H7/DCF_Valuation!$B$24)-1 -> 4.8477357 | K7: WC Days | L7: 63.480772
K8: WACC | L8: 0.079225061
K9: Terminal g | L9: 0.025

Sheet Output_Dashboard
A1: AUTO SECTOR - DCF VALUATION DASHBOARD
A2: Aurex Research | Akshat Gupta
A4: Scenario Selected | B4: =Control!B5 -> Severe Downside
A8: Intrinsic Value/share | B8: =CHOOSE(MATCH(Control!B5,{"Base Case","Mild Downside","Severe Downside","Upside"},0),Stress_Test!H4,Stress_Test!H5,Stress_Test!H6,Stress_Test!H7) -> 704.68 | D8: Key Assumptions
A9: Current Market Price/share | B9: =DCF_Valuation!B24 -> 363.25 | D9: Revenue Growth | E9: =CHOOSE(MATCH(Control!$B$5,{"Base Case","Mild Downside","Severe Downside","Upside"},0),Stress_Test!B4,Stress_Test!B5,Stress_Test!B6,Stress_Test!B7) -> 0.1022766
A10: Upside/Downside | B10: =(B8/B9)-1 -> 0.93993118 | D10: EBITDA Margin | E10: =CHOOSE(MATCH(Control!B5,{"Base Case","Mild Downside","Severe Downside","Upside"},0),Stress_Test!C4,Stress_Test!C5,Stress_Test!C6,Stress_Test!C7) -> 0.051829311
D11: Capex % of Revenue | E11: =CHOOSE(MATCH(Control!B5,{"Base Case","Mild Downside","Severe Downside","Upside"},0),Stress_Test!D4,Stress_Test!D5,Stress_Test!D6,Stress_Test!D7) -> 0.049662176
D12: Inventory Days | E12: =CHOOSE(MATCH(Control!B5,{"Base Case","Mild Downside","Severe Downside","Upside"},0),Stress_Test!E4,Stress_Test!E5,Stress_Test!E6,Stress_Test!E7) -> 73.480772
D13: WACC | E13: =CHOOSE(MATCH(Control!B5,{"Base Case","Mild Downside","Severe Downside","Upside"},0),Stress_Test!F4,Stress_Test!F5,Stress_Test!F6,Stress_Test!F7) -> 0.099225061
D14: Terminal g | E14: =CHOOSE( MATCH(Control!B5, {"Base Case","Mild Downside","Severe Downside","Upside"}, 0), Stress_Test!G4, Stress_Test!G5, Stress_Test!G6, Stress_Test!G7 ) -> 0.015
A16: Stress Test Summary
A18: =Stress_Test!A3 -> Scenario | B18: =Stress_Test!B3 -> Revenue Growth | C18: =Stress_Test!C3 -> EBITDA Margin | D18: =Stress_Test!D3 -> Capex % of Revenue | E18: =Stress_Test!E3 -> Inventory Days | F18: =Stress_Test!F3 -> WACC | G18: =Stress_Test!G3 -> Terminal g | H18: =Stress_Test!H3 -> Intrinsic Value | I18: =Stress_Test!I3 -> Upside/Downside
A19: =Stress_Test!A4 -> Base Case | B19: =Stress_Test!B4 -> 0.1522766 | C19: =Stress_Test!C4 -> 0.081829311 | D19: =Stress_Test!D4 -> 0.029662176 | E19: =Stress_Test!E4 -> 63.480772 | F19: =Stress_Test!F4 -> 0.079225061 | G19: =Stress_Test!G4 -> 0.025 | H19: =Stress_Test!H4 -> 1456.0144 | I19: =Stress_Test!I4 -> 3.0082984
A20: =Stress_Test!A5 -> Mild Downside | B20: =Stress_Test!B5 -> 0.1322766 | C20: =Stress_Test!C5 -> 0.071829311 | D20: =Stress_Test!D5 -> 0.039662176 | E20: =Stress_Test!E5 -> 68.480772 | F20: =Stress_Test!F5 -> 0.089225061 | G20: =Stress_Test!G5 -> 0.02 | H20: =Stress_Test!H5 -> 1004.68 | I20: =Stress_Test!I5 -> 1.7658087
A21: =Stress_Test!A6 -> Severe Downside | B21: =Stress_Test!B6 -> 0.1022766 | C21: =Stress_Test!C6 -> 0.051829311 | D21: =Stress_Test!D6 -> 0.049662176 | E21: =Stress_Test!E6 -> 73.480772 | F21: =Stress_Test!F6 -> 0.099225061 | G21: =Stress_Test!G6 -> 0.015 | H21: =Stress_Test!H6 -> 704.68 | I21: =Stress_Test!I6 -> 0.93993118
A22: =Stress_Test!A7 -> Upside | B22: =Stress_Test!B7 -> 0.1822766 | C22: =Stress_Test!C7 -> 0.096829311 | D22: =Stress_Test!D7 -> 0.019662176 | E22: =Stress_Test!E7 -> 58.480772 | F22: =Stress_Test!F7 -> 0.071725061 | G22: =Stress_Test!G7 -> 0.03 | H22: =Stress_Test!H7 -> 2124.19 | I22: =Stress_Test!I7 -> 4.8477357
A24: Interpretation & Key Takeaways
A25: Base case valuation implies ~313% upside, driven by strong growth and margin expansion assumptions.
A26: Even under Severe downside (lower growth, sharp margin compression, higher capex, and WACC near 10%), intrinsic value remains Rs. 705, suggesting ~100% from CMP.
A27: Valuation is highly sensitive to operating margins and cost of capital, highlighting the importance of execution discipline and macro stability.
A28: Upside scenario shows convexity in long-term cash flows, with intrinsic value exceeding ₹2,100 if growth and margins outperform.
A29: Overall, the stock appears deeply undervalued under a wide range of assumptions, but the investment case is critically dependent on sustained margin performance and capital efficiency.
