Workbook
Name ModelRange: DCF_Valuation!$A$1:$F$25

Sheet Control
A1: FMCG ROCE Compounding Model
A3: Company A | B3: #VALUE!
A4: Company B | B4: #VALUE!
A6: Base Year | B6: 2025
A7: Forecast Start | B7: 2026
A8: Forecast End | B8: 2030
A10: Currency | B10: INR Crores
A12: Model Purpose | B12: ROCE-driven compounding & valuation framework
A14: Scenario | B14: Base
A16: Scenario Index | B16: =MATCH(B14,{"Base","Mild","Severe","Upside"},0) -> 1

Sheet Assumptions
A1: Key Assumptions (FY2026-FY2030)
B3: HUL | C3: ITC
A5: Revenue Growth (%) | B5: =CHOOSE(MATCH(Control!B14,{"Base","Mild","Severe","Upside"},0),Stress_Helper!B13,Stress_Helper!B14,Stress_Helper!B15,Stress_Helper!B16) -> 0.022563928 | C5: =CHOOSE(MATCH(Control!B14,{"Base","Mild","Severe","Upside"},0),Stress_Helper!B21,Stress_Helper!B22,Stress_Helper!B23,Stress_Helper!B24) -> 0.092556862
A6: Long-term EBITDA Margin (%) | B6: 0.2335 | C6: 0.31588397
A7: EBIT Margin (%) | B7: =CHOOSE(MATCH(Control!B14,{"Base","Mild","Severe","Upside"},0),Stress_Helper!C13,Stress_Helper!C14,Stress_Helper!C15,Stress_Helper!C16) -> 0.226 | C7: =CHOOSE(MATCH(Control!B14,{"Base","Mild","Severe","Upside"},0),Stress_Helper!C21,Stress_Helper!C22,Stress_Helper!C23,Stress_Helper!C24) -> 0.308
A8: Effective Tax Rate (%) | B8: 0.25 | C8: 0.25
A9: Gross Margin (%) | B9: 0.503 | C9: 0.6113
A11: Dividend Payout (%) | B11: 0.95 | C11: 0.50730276
A12: Retention Ratio (%) | B12: =1-B11 -> 0.05 | C12: =1-C11 -> 0.49269724
A14: Terminal Growth Rate (%) | B14: =Sensitivity!J5 -> 0.03 | C14: =Sensitivity!K5 -> 0.03

Sheet ROCE_Drivers
A1: ROCE Drivers (FY2026-FY2030)
B4: FY2026 | C4: FY2027 | D4: FY2028 | E4: FY2029 | F4: FY2030 | G4: FY2031 | H4: FY2032 | I4: FY2033 | J4: FY2034 | K4: FY2035
A5: HUL
A6: EBIT Margin (%) | B6: =Assumptions!$B$7 -> 0.226 | C6: =B6+0.002 -> 0.228 | D6: =C6+0.002 -> 0.23 | E6: =D6+0.002 -> 0.232 | F6: =E6+0.002 -> 0.234 | G6: =F6+0.002 -> 0.236 | H6: =G6+0.002 -> 0.238 | I6: =H6+0.002 -> 0.24 | J6: =I6+0.002 -> 0.242 | K6: =J6+0.002 -> 0.244
A7: Capital Turnover (x) | B7: =B8/B6 -> 4.7876106 | C7: =$B$7 -> 4.7876106 | D7: =$B$7 -> 4.7876106 | E7: =$B$7 -> 4.7876106 | F7: =$B$7 -> 4.7876106 | G7: =$B$7 -> 4.7876106 | H7: =$B$7 -> 4.7876106 | I7: =$B$7 -> 4.7876106 | J7: =$B$7 -> 4.7876106 | K7: =$B$7 -> 4.7876106
A8: ROCE (%) | B8: 1.082 | C8: =C6*C7 -> 1.0915752 | D8: =D6*D7 -> 1.1011504 | E8: =E6*E7 -> 1.1107257 | F8: =F6*F7 -> 1.1203009 | G8: =G6*G7 -> 1.1298761 | H8: =H6*H7 -> 1.1394513 | I8: =I6*I7 -> 1.1490265 | J8: =J6*J7 -> 1.1586018 | K8: =K6*K7 -> 1.168177
A10: ITC
A11: EBIT Margin (%) | B11: =Assumptions!$C$7 -> 0.308 | C11: =B11+0.002 -> 0.31 | D11: =C11+0.002 -> 0.312 | E11: =D11+0.002 -> 0.314 | F11: =E11+0.002 -> 0.316 | G11: =F11+0.002 -> 0.318 | H11: =G11+0.002 -> 0.32 | I11: =H11+0.002 -> 0.322 | J11: =I11+0.002 -> 0.324 | K11: =J11+0.002 -> 0.326
A12: Capital Turnover (x) | B12: =B13/B11 -> 1.2594156 | C12: =$B$12 -> 1.2594156 | D12: =$B$12 -> 1.2594156 | E12: =$B$12 -> 1.2594156 | F12: =$B$12 -> 1.2594156 | G12: =$B$12 -> 1.2594156 | H12: =$B$12 -> 1.2594156 | I12: =$B$12 -> 1.2594156 | J12: =$B$12 -> 1.2594156 | K12: =$B$12 -> 1.2594156
A13: ROCE (%) | B13: 0.3879 | C13: =C11*C12 -> 0.39041883 | D13: =D11*D12 -> 0.39293766 | E13: =E11*E12 -> 0.39545649 | F13: =F11*F12 -> 0.39797532 | G13: =G11*G12 -> 0.40049416 | H13: =H11*H12 -> 0.40301299 | I13: =I11*I12 -> 0.40553182 | J13: =J11*J12 -> 0.40805065 | K13: =K11*K12 -> 0.41056948

Sheet Revenue_Drivers
A1: Revenue Drivers
B3: FY2025A | C3: FY2026F | D3: FY2027F | E3: FY2028F | F3: FY2029F | G3: FY2030F | H3: FY2031F | I3: FY2032F | J3: FY2033F | K3: FY2034F | L3: FY2035F
A5: HUL
A6: Revenue | B6: 64138 | C6: =B6*(1+B7) -> 65585.205 | D6: =C6*(1+C7) -> 67196.235 | E6: =D6*(1+D7) -> 68981.231 | F6: =E6*(1+E7) -> 70951.606 | G6: =F6*(1+F7) -> 73120.166 | H6: =G6*(1+G7) -> 75501.246 | I6: =H6*(1+H7) -> 78337.369 | J6: =I6*(1+I7) -> 81671.715 | ... L6: =K6*(1+K7) -> 90053.52
A7: YoY Growth (%) | B7: =Assumptions!B5 -> 0.022563928 | C7: =B7+0.2% -> 0.024563928 | D7: =C7+0.2% -> 0.026563928 | E7: =D7+0.2% -> 0.028563928 | F7: =E7+0.2% -> 0.030563928 | G7: =F7+0.2% -> 0.032563928 | H7: =G7+0.5% -> 0.037563928 | I7: =H7+0.5% -> 0.042563928 | J7: =I7+0.5% -> 0.047563928 | K7: =J7+0.5% -> 0.052563928 | L7: =K7+0.5% -> 0.057563928
A10: ITC
A11: Revenue | B11: 84142.47 | C11: =B11*(1+B12) -> 91930.433 | D11: =C11*(1+C12) -> 100623.09 | E11: =D11*(1+D12) -> 110338.94 | F11: =E11*(1+E12) -> 121213.59 | G11: =F11*(1+F12) -> 133402.45 | H11: =G11*(1+G12) -> 147083.79 | I11: =H11*(1+H12) -> 161874.08 | J11: =I11*(1+I12) -> 177827.88 | ... L11: =K11*(1+K12) -> 213436.81
A12: YoY Growth (%) | B12: =Assumptions!C5 -> 0.092556862 | C12: =B12+0.2% -> 0.094556862 | D12: =C12+0.2% -> 0.096556862 | E12: =D12+0.2% -> 0.098556862 | F12: =E12+0.2% -> 0.10055686 | G12: =F12+0.2% -> 0.10255686 | H12: =G12-0.2% -> 0.10055686 | I12: =H12-0.2% -> 0.098556862 | J12: =I12-0.2% -> 0.096556862 | K12: =J12-0.2% -> 0.094556862 | L12: =K12-0.2% -> 0.092556862

Sheet Operating_Margins
A1: Operating Margins
B3: FY2025A | C3: FY2026F | D3: FY2027F | E3: FY2028F | F3: FY2029F | G3: FY2030F | H3: FY2031F | I3: FY2032F | J3: FY2033F | K3: FY2034F | L3: FY2035F
A5: HUL
A6: Revenue | B6: =Revenue_Drivers!B6 -> 64138 | C6: =Revenue_Drivers!C6 -> 65585.205 | D6: =Revenue_Drivers!D6 -> 67196.235 | E6: =Revenue_Drivers!E6 -> 68981.231 | F6: =Revenue_Drivers!F6 -> 70951.606 | G6: =Revenue_Drivers!G6 -> 73120.166 | H6: =Revenue_Drivers!H6 -> 75501.246 | I6: =Revenue_Drivers!I6 -> 78337.369 | ... L6: =Revenue_Drivers!L6 -> 90053.52
A7: EBITDA Margin (%) | B7: =Assumptions!$B$6 -> 0.2335 | C7: =Assumptions!$B$6 -> 0.2335 | D7: =Assumptions!$B$6 -> 0.2335 | E7: =Assumptions!$B$6 -> 0.2335 | F7: =Assumptions!$B$6 -> 0.2335 | G7: =Assumptions!$B$6 -> 0.2335 | H7: =Assumptions!$B$6 -> 0.2335 | I7: =Assumptions!$B$6 -> 0.2335 | ... L7: =Assumptions!$B$6 -> 0.2335
A8: EBITDA | B8: =B6*B7 -> 14976.223 | C8: =C6*C7 -> 15314.145 | D8: =D6*D7 -> 15690.321 | E8: =E6*E7 -> 16107.118 | F8: =F6*F7 -> 16567.2 | G8: =G6*G7 -> 17073.559 | H8: =H6*H7 -> 17629.541 | I8: =I6*I7 -> 18291.776 | ... L8: =L6*L7 -> 21027.497
A9: EBIT Margin (%) | B9: =Assumptions!B7 -> 0.226 | C9: =ROCE_Drivers!B6 -> 0.226 | D9: =ROCE_Drivers!C6 -> 0.228 | E9: =ROCE_Drivers!D6 -> 0.23 | F9: =ROCE_Drivers!E6 -> 0.232 | G9: =ROCE_Drivers!F6 -> 0.234 | H9: =ROCE_Drivers!G6 -> 0.236 | I9: =ROCE_Drivers!H6 -> 0.238 | J9: =ROCE_Drivers!I6 -> 0.24 | ... L9: =ROCE_Drivers!K6 -> 0.244
A10: EBIT | B10: =B6*B9 -> 14495.188 | C10: =C6*C9 -> 14822.256 | D10: =D6*D9 -> 15320.742 | E10: =E6*E9 -> 15865.683 | F10: =F6*F9 -> 16460.773 | G10: =G6*G9 -> 17110.119 | H10: =H6*H9 -> 17818.294 | I10: =I6*I9 -> 18644.294 | ... L10: =L6*L9 -> 21973.059
A11: Gross Margin (%) | B11: =Assumptions!B9 -> 0.503 | C11: =B11-0.002 -> 0.501 | D11: =C11-0.002 -> 0.499 | E11: =D11-0.002 -> 0.497 | F11: =E11-0.002 -> 0.495 | G11: =F11-0.002 -> 0.493 | H11: =G11-0.002 -> 0.491 | I11: =H11-0.002 -> 0.489 | J11: =I11-0.002 -> 0.487 | ... L11: =K11-0.002 -> 0.483
A14: ITC
A15: Revenue | B15: =Revenue_Drivers!B11 -> 84142.47 | C15: =Revenue_Drivers!C11 -> 91930.433 | D15: =Revenue_Drivers!D11 -> 100623.09 | E15: =Revenue_Drivers!E11 -> 110338.94 | F15: =Revenue_Drivers!F11 -> 121213.59 | G15: =Revenue_Drivers!G11 -> 133402.45 | H15: =Revenue_Drivers!H11 -> 147083.79 | I15: =Revenue_Drivers!I11 -> 161874.08 | ... L15: =Revenue_Drivers!L11 -> 213436.81
A16: EBITDA Margin (%) | B16: =Assumptions!$C$6 -> 0.31588397 | C16: =Assumptions!$C$6 -> 0.31588397 | D16: =Assumptions!$C$6 -> 0.31588397 | E16: =Assumptions!$C$6 -> 0.31588397 | F16: =Assumptions!$C$6 -> 0.31588397 | G16: =Assumptions!$C$6 -> 0.31588397 | H16: =Assumptions!$C$6 -> 0.31588397 | I16: =Assumptions!$C$6 -> 0.31588397 | ... L16: =Assumptions!$C$6 -> 0.31588397
A17: EBITDA | B17: =B15*B16 -> 26579.257 | C17: =C15*C16 -> 29039.35 | D17: =D15*D16 -> 31785.219 | E17: =E15*E16 -> 34854.301 | F17: =F15*F16 -> 38289.431 | G17: =G15*G16 -> 42139.696 | H17: =H15*H16 -> 46461.411 | I17: =I15*I16 -> 51133.425 | ... L17: =L15*L16 -> 67421.267
A18: EBIT Margin (%) | B18: =Assumptions!C7 -> 0.308 | C18: =ROCE_Drivers!B11 -> 0.308 | D18: =ROCE_Drivers!C11 -> 0.31 | E18: =ROCE_Drivers!D11 -> 0.312 | F18: =ROCE_Drivers!E11 -> 0.314 | G18: =ROCE_Drivers!F11 -> 0.316 | H18: =ROCE_Drivers!G11 -> 0.318 | I18: =ROCE_Drivers!H11 -> 0.32 | J18: =ROCE_Drivers!I11 -> 0.322 | ... L18: =ROCE_Drivers!K11 -> 0.326
A19: EBIT | B19: =B15*B18 -> 25915.881 | C19: =C15*C18 -> 28314.573 | D19: =D15*D18 -> 31193.157 | E19: =E15*E18 -> 34425.748 | F19: =F15*F18 -> 38061.069 | G19: =G15*G18 -> 42155.175 | H19: =H15*H18 -> 46772.645 | I19: =I15*I18 -> 51799.704 | ... L19: =L15*L18 -> 69580.401
A20: Gross Margin (%) | B20: =Assumptions!C9 -> 0.6113 | C20: =B20-0.002 -> 0.6093 | D20: =C20-0.002 -> 0.6073 | E20: =D20-0.002 -> 0.6053 | F20: =E20-0.002 -> 0.6033 | G20: =F20-0.002 -> 0.6013 | H20: =G20-0.002 -> 0.5993 | I20: =H20-0.002 -> 0.5973 | J20: =I20-0.002 -> 0.5953 | ... L20: =K20-0.002 -> 0.5913

Sheet Working_Capital
A1: Working Capital
B3: FY2025A | C3: FY2026F | D3: FY2027F | E3: FY2028F | F3: FY2029F | G3: FY2030F | H3: FY2031F | I3: FY2032F | J3: FY2033F | K3: FY2034F | L3: FY2035F
A5: HUL
A6: Revenue | B6: =Operating_Margins!B6 -> 64138 | C6: =Operating_Margins!C6 -> 65585.205 | D6: =Operating_Margins!D6 -> 67196.235 | E6: =Operating_Margins!E6 -> 68981.231 | F6: =Operating_Margins!F6 -> 70951.606 | G6: =Operating_Margins!G6 -> 73120.166 | H6: =Operating_Margins!H6 -> 75501.246 | I6: =Operating_Margins!I6 -> 78337.369 | ... L6: =Operating_Margins!L6 -> 90053.52
A7: Gross Profit | B7: =B6*Operating_Margins!B11 -> 32261.414 | C7: =C6*Operating_Margins!C11 -> 32858.188 | D7: =D6*Operating_Margins!D11 -> 33530.921 | E7: =E6*Operating_Margins!E11 -> 34283.672 | F7: =F6*Operating_Margins!F11 -> 35121.045 | G7: =G6*Operating_Margins!G11 -> 36048.242 | H7: =H6*Operating_Margins!H11 -> 37071.112 | I7: =I6*Operating_Margins!I11 -> 38306.974 | ... L7: =L6*Operating_Margins!L11 -> 43495.85
A8: COGS | B8: =B6-B7 -> 31876.586 | C8: =C6-C7 -> 32727.017 | D8: =D6-D7 -> 33665.314 | E8: =E6-E7 -> 34697.559 | F8: =F6-F7 -> 35830.561 | G8: =G6-G7 -> 37071.924 | H8: =H6-H7 -> 38430.134 | I8: =I6-I7 -> 40030.396 | ... L8: =L6-L7 -> 46557.67
A9: Inventory Days | B9: =CHOOSE(MATCH(Control!B14,{"Base","Mild","Severe","Upside"},0),Stress_Helper!E13,Stress_Helper!E14,Stress_Helper!E15,Stress_Helper!E16) -> 50.553563 | C9: =B9 -> 50.553563 | D9: =C9 -> 50.553563 | E9: =D9 -> 50.553563 | F9: =E9 -> 50.553563 | G9: =F9 -> 50.553563 | H9: =G9 -> 50.553563 | I9: =H9 -> 50.553563 | J9: =I9 -> 50.553563 | ... L9: =K9 -> 50.553563
A10: Receivable Days | B10: =B13/B6*365 -> 21.733372 | C10: =B10 -> 21.733372 | D10: =C10 -> 21.733372 | E10: =D10 -> 21.733372 | F10: =E10 -> 21.733372 | G10: =F10 -> 21.733372 | H10: =G10 -> 21.733372 | I10: =H10 -> 21.733372 | J10: =I10 -> 21.733372 | ... L10: =K10 -> 21.733372
A11: Payable Days | B11: =B14/B8*365 -> 129.5614 | C11: =B11 -> 129.5614 | D11: =C11 -> 129.5614 | E11: =D11 -> 129.5614 | F11: =E11 -> 129.5614 | G11: =F11 -> 129.5614 | H11: =G11 -> 129.5614 | I11: =H11 -> 129.5614 | J11: =I11 -> 129.5614 | ... L11: =K11 -> 129.5614
A12: Inventory | B12: 4415 | C12: =C8*C9/365 -> 4532.7872 | D12: =D8*D9/365 -> 4662.744 | E12: =E8*E9/365 -> 4805.713 | F12: =F8*F9/365 -> 4962.6371 | G12: =G8*G9/365 -> 5134.5695 | H12: =H8*H9/365 -> 5322.6855 | I12: =I8*I9/365 -> 5544.3264 | J12: =J8*J9/365 -> 5802.9382 | ... L12: =L8*L9/365 -> 6448.3729
A13: Receivables | B13: 3819 | C13: =C6*C10/365 -> 3905.1716 | D13: =D6*D10/365 -> 4001.098 | E13: =E6*E10/365 -> 4107.3829 | F13: =F6*F10/365 -> 4224.7059 | G13: =G6*G10/365 -> 4353.8295 | H13: =H6*H10/365 -> 4495.6073 | I13: =I6*I10/365 -> 4664.4799 | J13: =J6*J10/365 -> 4863.0185 | ... L13: =L6*L10/365 -> 5362.1004
A14: Payables | B14: =263+11052 -> 11315 | C14: =C8*C11/365 -> 11616.871 | D14: =D8*D11/365 -> 11949.932 | E14: =E8*E11/365 -> 12316.34 | F14: =F8*F11/365 -> 12718.514 | G14: =G8*G11/365 -> 13159.151 | H14: =H8*H11/365 -> 13641.265 | I14: =I8*I11/365 -> 14209.299 | J14: =J8*J11/365 -> 14872.083 | ... L14: =L8*L11/365 -> 16526.238
A15: Net Working Capital | B15: =B12+B13-B14 -> -3081 | C15: =C12+C13-C14 -> -3178.9126 | D15: =D12+D13-D14 -> -3286.0897 | E15: =E12+E13-E14 -> -3403.2445 | F15: =F12+F13-F14 -> -3531.1709 | G15: =G12+G13-G14 -> -3670.7525 | H15: =H12+H13-H14 -> -3822.9726 | I15: =I12+I13-I14 -> -4000.4922 | ... L15: =L12+L13-L14 -> -4715.7644
A16: Change in WC | B16: 0 | C16: =C15-B15 -> -97.912585 | D16: =D15-C15 -> -107.17715 | E16: =E15-D15 -> -117.15478 | F16: =F15-E15 -> -127.92637 | G16: =G15-F15 -> -139.58161 | H16: =H15-G15 -> -152.22009 | I16: =I15-H15 -> -177.51965 | J16: =J15-I15 -> -205.63395 | ... L16: =L15-K15 -> -272.5393
A19: ITC
A20: Revenue | B20: =Operating_Margins!B15 -> 84142.47 | C20: =Operating_Margins!C15 -> 91930.433 | D20: =Operating_Margins!D15 -> 100623.09 | E20: =Operating_Margins!E15 -> 110338.94 | F20: =Operating_Margins!F15 -> 121213.59 | G20: =Operating_Margins!G15 -> 133402.45 | H20: =Operating_Margins!H15 -> 147083.79 | I20: =Operating_Margins!I15 -> 161874.08 | ... L20: =Operating_Margins!L15 -> 213436.81
A21: Gross Profit | B21: =B20*Operating_Margins!B20 -> 51436.292 | C21: =C20*Operating_Margins!C20 -> 56013.213 | D21: =D20*Operating_Margins!D20 -> 61108.4 | E21: =E20*Operating_Margins!E20 -> 66788.158 | F21: =F20*Operating_Margins!F20 -> 73128.162 | G21: =G20*Operating_Margins!G20 -> 80214.895 | H21: =H20*Operating_Margins!H20 -> 88147.316 | I21: =I20*Operating_Margins!I20 -> 96687.385 | ... L21: =L20*Operating_Margins!L20 -> 126205.19
A22: COGS | B22: =B20-B21 -> 32706.178 | C22: =C20-C21 -> 35917.22 | D22: =D20-D21 -> 39514.686 | E22: =E20-E21 -> 43550.778 | F22: =F20-F21 -> 48085.433 | G22: =G20-G21 -> 53187.558 | H22: =H20-H21 -> 58936.475 | I22: =I20-I21 -> 65186.69 | ... L22: =L20-L21 -> 87231.625
A23: Inventory Days | B23: =CHOOSE(MATCH(Control!B14,{"Base","Mild","Severe","Upside"},0),Stress_Helper!E21,Stress_Helper!E22,Stress_Helper!E23,Stress_Helper!E24) -> 174.51472 | C23: =B23 -> 174.51472 | D23: =C23 -> 174.51472 | E23: =D23 -> 174.51472 | F23: =E23 -> 174.51472 | G23: =F23 -> 174.51472 | H23: =G23 -> 174.51472 | I23: =H23 -> 174.51472 | J23: =I23 -> 174.51472 | ... L23: =K23 -> 174.51472
A24: Receivable Days | B24: =B27/B20*365 -> 20.473366 | C24: =B24 -> 20.473366 | D24: =C24 -> 20.473366 | E24: =D24 -> 20.473366 | F24: =E24 -> 20.473366 | G24: =F24 -> 20.473366 | H24: =G24 -> 20.473366 | I24: =H24 -> 20.473366 | J24: =I24 -> 20.473366 | ... L24: =K24 -> 20.473366
A25: Payable Days | B25: =B28/B22*365 -> 53.649329 | C25: =B25 -> 53.649329 | D25: =C25 -> 53.649329 | E25: =D25 -> 53.649329 | F25: =E25 -> 53.649329 | G25: =F25 -> 53.649329 | H25: =G25 -> 53.649329 | I25: =H25 -> 53.649329 | J25: =I25 -> 53.649329 | ... L25: =K25 -> 53.649329
A26: Inventory | B26: 15637.56 | C26: =C22*C23/365 -> 17172.832 | D26: =D22*D23/365 -> 18892.861 | E26: =E22*E23/365 -> 20822.607 | F26: =F22*F23/365 -> 22990.728 | G26: =G22*G23/365 -> 25430.169 | H26: =H22*H23/365 -> 28178.855 | I26: =I22*I23/365 -> 31167.224 | J26: =J22*J23/365 -> 34409.015 | ... L26: =L22*L23/365 -> 41707.404
A27: Receivables | B27: 4719.67 | C27: =C20*C24/365 -> 5156.5078 | D27: =D20*D24/365 -> 5644.091 | E27: =E20*E24/365 -> 6189.0668 | F27: =F20*F24/365 -> 6799.0418 | G27: =G20*G24/365 -> 7482.7321 | H27: =H20*H24/365 -> 8250.1376 | I27: =I20*I24/365 -> 9079.7455 | J27: =J20*J24/365 -> 9974.6168 | ... L27: =L20*L24/365 -> 11971.972
A28: Payables | B28: =180.64+4626.66 -> 4807.3 | C28: =C22*C25/365 -> 5279.2733 | D28: =D22*D25/365 -> 5808.0449 | E28: =E22*E25/365 -> 6401.2877 | F28: =F22*F25/365 -> 7067.8115 | G28: =G22*G25/365 -> 7817.7447 | H28: =H22*H25/365 -> 8662.7461 | I28: =I22*I25/365 -> 9581.4306 | J28: =J22*J25/365 -> 10578.022 | ... L28: =L22*L25/365 -> 12821.694
A29: Net Working Capital | B29: =B26+B27-B28 -> 15549.93 | C29: =C26+C27-C28 -> 17050.066 | D29: =D26+D27-D28 -> 18728.907 | E29: =E26+E27-E28 -> 20610.386 | F29: =F26+F27-F28 -> 22721.958 | G29: =G26+G27-G28 -> 25095.156 | H29: =H26+H27-H28 -> 27766.247 | I29: =I26+I27-I28 -> 30665.539 | ... L29: =L26+L27-L28 -> 40857.683
A30: Change in WC | B30: 0 | C30: =C29-B29 -> 1500.1361 | D30: =D29-C29 -> 1678.841 | E30: =E29-D29 -> 1881.4793 | F30: =F29-E29 -> 2111.5719 | G30: =G29-F29 -> 2373.1981 | H30: =H29-G29 -> 2671.0906 | I30: =I29-H29 -> 2899.292 | J30: =J29-I29 -> 3140.0704 | ... L30: =L29-K29 -> 3658.7668

Sheet Capex_Depreciation
A1: Capex & Depreciation
B3: FY2025A | C3: FY2026F | D3: FY2027F | E3: FY2028F | F3: FY2029F | G3: FY2030F | H3: FY2031F | I3: FY2032F | J3: FY2033F | K3: FY2034F | L3: FY2035F
A5: HUL
A6: Revenue | B6: =Working_Capital!B6 -> 64138 | C6: =Working_Capital!C6 -> 65585.205 | D6: =Working_Capital!D6 -> 67196.235 | E6: =Working_Capital!E6 -> 68981.231 | F6: =Working_Capital!F6 -> 70951.606 | G6: =Working_Capital!G6 -> 73120.166 | H6: =Working_Capital!H6 -> 75501.246 | I6: =Working_Capital!I6 -> 78337.369 | ... L6: =Working_Capital!L6 -> 90053.52
A7: Capex % of revenue | B7: =CHOOSE(MATCH(Control!B14,{"Base","Mild","Severe","Upside"},0),Stress_Helper!D13,Stress_Helper!D14,Stress_Helper!D15,Stress_Helper!D16) -> 0.019551592 | C7: =B7 -> 0.019551592 | D7: =C7 -> 0.019551592 | E7: =D7 -> 0.019551592 | F7: =E7 -> 0.019551592 | G7: =F7 -> 0.019551592 | H7: =G7 -> 0.019551592 | I7: =H7 -> 0.019551592 | J7: =I7 -> 0.019551592 | ... L7: =K7 -> 0.019551592
A8: Capex | B8: 1254 | C8: =C6*C7 -> 1282.2952 | D8: =D6*D7 -> 1313.7934 | E8: =E6*E7 -> 1348.6929 | F8: =F6*F7 -> 1387.2168 | G8: =G6*G7 -> 1429.6156 | H8: =H6*H7 -> 1476.1695 | I8: =I6*I7 -> 1531.6203 | J8: =J6*J7 -> 1596.812 | ... L8: =L6*L7 -> 1760.6897
A9: Opening Net PPE | B9: 8031 | C9: =B11 -> 8625 | D9: =C11 -> 8601.3557 | E9: =D11 -> 8612.7896 | F9: =E11 -> 8657.3918 | G9: =F11 -> 8733.7647 | H9: =G11 -> 8840.9724 | I9: =H11 -> 8978.5014 | J9: =I11 -> 9150.6574 | ... L9: =K11 -> 9617.1794
A10: Depreciation | B10: 1216 | C10: =(B10/B9)*C9 -> 1305.9395 | D10: =(C10/C9)*D9 -> 1302.3594 | E10: =(D10/D9)*E9 -> 1304.0907 | F10: =(E10/E9)*F9 -> 1310.844 | G10: =(F10/F9)*G9 -> 1322.4079 | H10: =(G10/G9)*H9 -> 1338.6406 | I10: =(H10/H9)*I9 -> 1359.4643 | J10: =(I10/I9)*J9 -> 1385.531 | ... L10: =(K10/K9)*L9 -> 1456.1686
A11: Closing Net PPE | B11: 8625 | C11: =C9+C8-C10 -> 8601.3557 | D11: =D9+D8-D10 -> 8612.7896 | E11: =E9+E8-E10 -> 8657.3918 | F11: =F9+F8-F10 -> 8733.7647 | G11: =G9+G8-G10 -> 8840.9724 | H11: =H9+H8-H10 -> 8978.5014 | I11: =I9+I8-I10 -> 9150.6574 | J11: =J9+J8-J10 -> 9361.9384 | ... L11: =L9+L8-L10 -> 9921.7004
A14: ITC
A15: Revenue | B15: =Working_Capital!B20 -> 84142.47 | C15: =Working_Capital!C20 -> 91930.433 | D15: =Working_Capital!D20 -> 100623.09 | E15: =Working_Capital!E20 -> 110338.94 | F15: =Working_Capital!F20 -> 121213.59 | G15: =Working_Capital!G20 -> 133402.45 | H15: =Working_Capital!H20 -> 147083.79 | I15: =Working_Capital!I20 -> 161874.08 | ... L15: =Working_Capital!L20 -> 213436.81
A16: Capex % of revenue | B16: =CHOOSE(MATCH(Control!B14,{"Base","Mild","Severe","Upside"},0),Stress_Helper!D21,Stress_Helper!D22,Stress_Helper!D23,Stress_Helper!D24) -> 0.027081449 | C16: =B16 -> 0.027081449 | D16: =C16 -> 0.027081449 | E16: =D16 -> 0.027081449 | F16: =E16 -> 0.027081449 | G16: =F16 -> 0.027081449 | H16: =G16 -> 0.027081449 | I16: =H16 -> 0.027081449 | J16: =I16 -> 0.027081449 | ... L16: =K16 -> 0.027081449
A17: Capex | B17: 2278.7 | C17: =C15*C16 -> 2489.6093 | D17: =D15*D16 -> 2725.019 | E17: =E15*E16 -> 2988.1382 | F17: =F15*F16 -> 3282.6398 | G17: =G15*G16 -> 3612.7317 | H17: =H15*H16 -> 3983.2422 | I17: =I15*I16 -> 4383.7845 | J17: =J15*J16 -> 4815.8365 | ... L17: =L15*L16 -> 5780.1781
A18: Opening Net PPE | B18: 23082.33 | C18: =B20 -> 17428.89 | D18: =C20 -> 18772.295 | E18: =D20 -> 20262.762 | F18: =E20 -> 21918.328 | G18: =F20 -> 23759.518 | H18: =G20 -> 25809.715 | I18: =H20 -> 28095.592 | J18: =I20 -> 30631.681 | ... L18: =K20 -> 36515.166
A19: Depreciation | B19: 1518 | C19: =(B19/B18)*C18 -> 1146.2038 | D19: =(C19/C18)*D18 -> 1234.5523 | E19: =(D19/D18)*E18 -> 1332.5723 | F19: =(E19/E18)*F18 -> 1441.4499 | G19: =(F19/F18)*G18 -> 1562.535 | H19: =(G19/G18)*H18 -> 1697.3653 | I19: =(H19/H18)*I18 -> 1847.6951 | J19: =(I19/I18)*J18 -> 2014.48 | ... L19: =(K19/K18)*L18 -> 2401.405
A20: Closing Net PPE | B20: 17428.89 | C20: =C18+C17-C19 -> 18772.295 | D20: =D18+D17-D19 -> 20262.762 | E20: =E18+E17-E19 -> 21918.328 | F20: =F18+F17-F19 -> 23759.518 | G20: =G18+G17-G19 -> 25809.715 | H20: =H18+H17-H19 -> 28095.592 | I20: =I18+I17-I19 -> 30631.681 | J20: =J18+J17-J19 -> 33433.037 | ... L20: =L18+L17-L19 -> 39893.939

Sheet Income-Statement
A1: Income Statement
B3: FY2025A | C3: FY2026F | D3: FY2027F | E3: FY2028F | F3: FY2029F | G3: FY2030F | H3: FY2031F | I3: FY2032F | J3: FY2033F | K3: FY2034F | L3: FY2035F
A5: HUL
A6: Revenue | B6: =Capex_Depreciation!B6 -> 64138 | C6: =Capex_Depreciation!C6 -> 65585.205 | D6: =Capex_Depreciation!D6 -> 67196.235 | E6: =Capex_Depreciation!E6 -> 68981.231 | F6: =Capex_Depreciation!F6 -> 70951.606 | G6: =Capex_Depreciation!G6 -> 73120.166 | H6: =Capex_Depreciation!H6 -> 75501.246 | I6: =Capex_Depreciation!I6 -> 78337.369 | ... L6: =Capex_Depreciation!L6 -> 90053.52
A7: EBITDA | B7: =Operating_Margins!B8 -> 14976.223 | C7: =Operating_Margins!C8 -> 15314.145 | D7: =Operating_Margins!D8 -> 15690.321 | E7: =Operating_Margins!E8 -> 16107.118 | F7: =Operating_Margins!F8 -> 16567.2 | G7: =Operating_Margins!G8 -> 17073.559 | H7: =Operating_Margins!H8 -> 17629.541 | I7: =Operating_Margins!I8 -> 18291.776 | ... L7: =Operating_Margins!L8 -> 21027.497
A8: Depreciation | B8: =Capex_Depreciation!B10 -> 1216 | C8: =Capex_Depreciation!C10 -> 1305.9395 | D8: =Capex_Depreciation!D10 -> 1302.3594 | E8: =Capex_Depreciation!E10 -> 1304.0907 | F8: =Capex_Depreciation!F10 -> 1310.844 | G8: =Capex_Depreciation!G10 -> 1322.4079 | H8: =Capex_Depreciation!H10 -> 1338.6406 | I8: =Capex_Depreciation!I10 -> 1359.4643 | ... L8: =Capex_Depreciation!L10 -> 1456.1686
A9: EBIT | B9: =Operating_Margins!B10 -> 14495.188 | C9: =Operating_Margins!C10 -> 14822.256 | D9: =Operating_Margins!D10 -> 15320.742 | E9: =Operating_Margins!E10 -> 15865.683 | F9: =Operating_Margins!F10 -> 16460.773 | G9: =Operating_Margins!G10 -> 17110.119 | H9: =Operating_Margins!H10 -> 17818.294 | I9: =Operating_Margins!I10 -> 18644.294 | ... L9: =Operating_Margins!L10 -> 21973.059
A10: Tax | B10: =B9*Assumptions!$B$8 -> 3623.797 | C10: =C9*Assumptions!$B$8 -> 3705.5641 | D10: =D9*Assumptions!$B$8 -> 3830.1854 | E10: =E9*Assumptions!$B$8 -> 3966.4208 | F10: =F9*Assumptions!$B$8 -> 4115.1932 | G10: =G9*Assumptions!$B$8 -> 4277.5297 | H10: =H9*Assumptions!$B$8 -> 4454.5735 | I10: =I9*Assumptions!$B$8 -> 4661.0735 | ... L10: =L9*Assumptions!$B$8 -> 5493.2647
A11: NOPAT | B11: =B9-B10 -> 10871.391 | C11: =C9-C10 -> 11116.692 | D11: =D9-D10 -> 11490.556 | E11: =E9-E10 -> 11899.262 | F11: =F9-F10 -> 12345.579 | G11: =G9-G10 -> 12832.589 | H11: =H9-H10 -> 13363.721 | I11: =I9-I10 -> 13983.22 | ... L11: =L9-L10 -> 16479.794
A14: ITC
A15: Revenue | B15: =Capex_Depreciation!B15 -> 84142.47 | C15: =Capex_Depreciation!C15 -> 91930.433 | D15: =Capex_Depreciation!D15 -> 100623.09 | E15: =Capex_Depreciation!E15 -> 110338.94 | F15: =Capex_Depreciation!F15 -> 121213.59 | G15: =Capex_Depreciation!G15 -> 133402.45 | H15: =Capex_Depreciation!H15 -> 147083.79 | I15: =Capex_Depreciation!I15 -> 161874.08 | ... L15: =Capex_Depreciation!L15 -> 213436.81
A16: EBITDA | B16: =Operating_Margins!B17 -> 26579.257 | C16: =Operating_Margins!C17 -> 29039.35 | D16: =Operating_Margins!D17 -> 31785.219 | E16: =Operating_Margins!E17 -> 34854.301 | F16: =Operating_Margins!F17 -> 38289.431 | G16: =Operating_Margins!G17 -> 42139.696 | H16: =Operating_Margins!H17 -> 46461.411 | I16: =Operating_Margins!I17 -> 51133.425 | ... L16: =Operating_Margins!L17 -> 67421.267
A17: Depreciation | B17: =Capex_Depreciation!B19 -> 1518 | C17: =Capex_Depreciation!C19 -> 1146.2038 | D17: =Capex_Depreciation!D19 -> 1234.5523 | E17: =Capex_Depreciation!E19 -> 1332.5723 | F17: =Capex_Depreciation!F19 -> 1441.4499 | G17: =Capex_Depreciation!G19 -> 1562.535 | H17: =Capex_Depreciation!H19 -> 1697.3653 | I17: =Capex_Depreciation!I19 -> 1847.6951 | ... L17: =Capex_Depreciation!L19 -> 2401.405
A18: EBIT | B18: =Operating_Margins!B19 -> 25915.881 | C18: =Operating_Margins!C19 -> 28314.573 | D18: =Operating_Margins!D19 -> 31193.157 | E18: =Operating_Margins!E19 -> 34425.748 | F18: =Operating_Margins!F19 -> 38061.069 | G18: =Operating_Margins!G19 -> 42155.175 | H18: =Operating_Margins!H19 -> 46772.645 | I18: =Operating_Margins!I19 -> 51799.704 | ... L18: =Operating_Margins!L19 -> 69580.401
A19: Tax | B19: =B18*Assumptions!$C$8 -> 6478.9702 | C19: =C18*Assumptions!$C$8 -> 7078.6433 | D19: =D18*Assumptions!$C$8 -> 7798.2892 | E19: =E18*Assumptions!$C$8 -> 8606.437 | F19: =F18*Assumptions!$C$8 -> 9515.2672 | G19: =G18*Assumptions!$C$8 -> 10538.794 | H19: =H18*Assumptions!$C$8 -> 11693.161 | I19: =I18*Assumptions!$C$8 -> 12949.926 | ... L19: =L18*Assumptions!$C$8 -> 17395.1
A20: NOPAT | B20: =B18-B19 -> 19436.911 | C20: =C18-C19 -> 21235.93 | D20: =D18-D19 -> 23394.868 | E20: =E18-E19 -> 25819.311 | F20: =F18-F19 -> 28545.802 | G20: =G18-G19 -> 31616.382 | H20: =H18-H19 -> 35079.484 | I20: =I18-I19 -> 38849.778 | ... L20: =L18-L19 -> 52185.301

Sheet Balance_Sheet
A1: Balance Sheet (ROCE Focus)
B3: FY2025A | C3: FY2026F | D3: FY2027F | E3: FY2028F | F3: FY2029F | G3: FY2030F | H3: FY2031F | I3: FY2032F | J3: FY2033F | K3: FY2034F | L3: FY2035F
A5: HUL
A6: Net PPE | B6: =Capex_Depreciation!B11 -> 8625 | C6: =Capex_Depreciation!C11 -> 8601.3557 | D6: =Capex_Depreciation!D11 -> 8612.7896 | E6: =Capex_Depreciation!E11 -> 8657.3918 | F6: =Capex_Depreciation!F11 -> 8733.7647 | G6: =Capex_Depreciation!G11 -> 8840.9724 | H6: =Capex_Depreciation!H11 -> 8978.5014 | I6: =Capex_Depreciation!I11 -> 9150.6574 | ... L6: =Capex_Depreciation!L11 -> 9921.7004
A7: Net Working Capital | B7: =Working_Capital!B15 -> -3081 | C7: =Working_Capital!C15 -> -3178.9126 | D7: =Working_Capital!D15 -> -3286.0897 | E7: =Working_Capital!E15 -> -3403.2445 | F7: =Working_Capital!F15 -> -3531.1709 | G7: =Working_Capital!G15 -> -3670.7525 | H7: =Working_Capital!H15 -> -3822.9726 | I7: =Working_Capital!I15 -> -4000.4922 | ... L7: =Working_Capital!L15 -> -4715.7644
A8: Other Operating Assets | B8: =28244+1009 -> 29253 | C8: =B8 -> 29253 | D8: =C8 -> 29253 | E8: =D8 -> 29253 | F8: =E8 -> 29253 | G8: =F8 -> 29253 | H8: =G8 -> 29253 | I8: =H8 -> 29253 | J8: =I8 -> 29253 | ... L8: =K8 -> 29253
A9: Capital Employed | B9: =B6+B7+B8 -> 34797 | C9: =C6+C7+C8 -> 34675.443 | D9: =D6+D7+D8 -> 34579.7 | E9: =E6+E7+E8 -> 34507.147 | F9: =F6+F7+F8 -> 34455.594 | G9: =G6+G7+G8 -> 34423.22 | H9: =H6+H7+H8 -> 34408.529 | I9: =I6+I7+I8 -> 34403.165 | ... L9: =L6+L7+L8 -> 34458.936
A12: ITC
A13: Net PPE | B13: =Capex_Depreciation!B20 -> 17428.89 | C13: =Capex_Depreciation!C20 -> 18772.295 | D13: =Capex_Depreciation!D20 -> 20262.762 | E13: =Capex_Depreciation!E20 -> 21918.328 | F13: =Capex_Depreciation!F20 -> 23759.518 | G13: =Capex_Depreciation!G20 -> 25809.715 | H13: =Capex_Depreciation!H20 -> 28095.592 | I13: =Capex_Depreciation!I20 -> 30631.681 | ... L13: =Capex_Depreciation!L20 -> 39893.939
A14: Net Working Capital | B14: =Working_Capital!B29 -> 15549.93 | C14: =Working_Capital!C29 -> 17050.066 | D14: =Working_Capital!D29 -> 18728.907 | E14: =Working_Capital!E29 -> 20610.386 | F14: =Working_Capital!F29 -> 22721.958 | G14: =Working_Capital!G29 -> 25095.156 | H14: =Working_Capital!H29 -> 27766.247 | I14: =Working_Capital!I29 -> 30665.539 | ... L14: =Working_Capital!L29 -> 40857.683
A15: Other Operating Assets | B15: =1087.6+2724.74 -> 3812.34 | C15: =B15 -> 3812.34 | D15: =C15 -> 3812.34 | E15: =D15 -> 3812.34 | F15: =E15 -> 3812.34 | G15: =F15 -> 3812.34 | H15: =G15 -> 3812.34 | I15: =H15 -> 3812.34 | J15: =I15 -> 3812.34 | ... L15: =K15 -> 3812.34
A16: Capital Employed | B16: =B13+B14+B15 -> 36791.16 | C16: =C13+C14+C15 -> 39634.702 | D16: =D13+D14+D15 -> 42804.009 | E16: =E13+E14+E15 -> 46341.054 | F16: =F13+F14+F15 -> 50293.816 | G16: =G13+G14+G15 -> 54717.211 | H16: =H13+H14+H15 -> 59674.178 | I16: =I13+I14+I15 -> 65109.56 | ... L16: =L13+L14+L15 -> 84563.962

Sheet Cash_Flow (FCFF)
A1: Free Cash Flow to Firm
B3: FY2025A | C3: FY2026F | D3: FY2027F | E3: FY2028F | F3: FY2029F | G3: FY2030F | H3: FY2031F | I3: FY2032F | J3: FY2033F | K3: FY2034F | L3: FY2035F
A5: HUL
A6: NOPAT | B6: ='Income-Statement'!B11 -> 10871.391 | C6: ='Income-Statement'!C11 -> 11116.692 | D6: ='Income-Statement'!D11 -> 11490.556 | E6: ='Income-Statement'!E11 -> 11899.262 | F6: ='Income-Statement'!F11 -> 12345.579 | G6: ='Income-Statement'!G11 -> 12832.589 | H6: ='Income-Statement'!H11 -> 13363.721 | I6: ='Income-Statement'!I11 -> 13983.22 | ... L6: ='Income-Statement'!L11 -> 16479.794
A7: Depreciation | B7: ='Income-Statement'!B8 -> 1216 | C7: ='Income-Statement'!C8 -> 1305.9395 | D7: ='Income-Statement'!D8 -> 1302.3594 | E7: ='Income-Statement'!E8 -> 1304.0907 | F7: ='Income-Statement'!F8 -> 1310.844 | G7: ='Income-Statement'!G8 -> 1322.4079 | H7: ='Income-Statement'!H8 -> 1338.6406 | I7: ='Income-Statement'!I8 -> 1359.4643 | ... L7: ='Income-Statement'!L8 -> 1456.1686
A8: Capex | B8: =Capex_Depreciation!B8 -> 1254 | C8: =Capex_Depreciation!C8 -> 1282.2952 | D8: =Capex_Depreciation!D8 -> 1313.7934 | E8: =Capex_Depreciation!E8 -> 1348.6929 | F8: =Capex_Depreciation!F8 -> 1387.2168 | G8: =Capex_Depreciation!G8 -> 1429.6156 | H8: =Capex_Depreciation!H8 -> 1476.1695 | I8: =Capex_Depreciation!I8 -> 1531.6203 | ... L8: =Capex_Depreciation!L8 -> 1760.6897
A9: Change in NWC | B9: =Working_Capital!B16 -> 0 | C9: =Working_Capital!C16 -> -97.912585 | D9: =Working_Capital!D16 -> -107.17715 | E9: =Working_Capital!E16 -> -117.15478 | F9: =Working_Capital!F16 -> -127.92637 | G9: =Working_Capital!G16 -> -139.58161 | H9: =Working_Capital!H16 -> -152.22009 | I9: =Working_Capital!I16 -> -177.51965 | ... L9: =Working_Capital!L16 -> -272.5393
A10: FCFF | B10: =B6+B7-B8-B9 -> 10833.391 | C10: =C6+C7-C8-C9 -> 11238.249 | D10: =D6+D7-D8-D9 -> 11586.299 | E10: =E6+E7-E8-E9 -> 11971.815 | F10: =F6+F7-F8-F9 -> 12397.133 | G10: =G6+G7-G8-G9 -> 12864.963 | H10: =H6+H7-H8-H9 -> 13378.412 | I10: =I6+I7-I8-I9 -> 13988.584 | ... L10: =L6+L7-L8-L9 -> 16447.812
A13: ITC
A14: NOPAT | B14: ='Income-Statement'!B20 -> 19436.911 | C14: ='Income-Statement'!C20 -> 21235.93 | D14: ='Income-Statement'!D20 -> 23394.868 | E14: ='Income-Statement'!E20 -> 25819.311 | F14: ='Income-Statement'!F20 -> 28545.802 | G14: ='Income-Statement'!G20 -> 31616.382 | H14: ='Income-Statement'!H20 -> 35079.484 | I14: ='Income-Statement'!I20 -> 38849.778 | ... L14: ='Income-Statement'!L20 -> 52185.301
A15: Depreciation | B15: ='Income-Statement'!B17 -> 1518 | C15: ='Income-Statement'!C17 -> 1146.2038 | D15: ='Income-Statement'!D17 -> 1234.5523 | E15: ='Income-Statement'!E17 -> 1332.5723 | F15: ='Income-Statement'!F17 -> 1441.4499 | G15: ='Income-Statement'!G17 -> 1562.535 | H15: ='Income-Statement'!H17 -> 1697.3653 | I15: ='Income-Statement'!I17 -> 1847.6951 | ... L15: ='Income-Statement'!L17 -> 2401.405
A16: Capex | B16: =Capex_Depreciation!B17 -> 2278.7 | C16: =Capex_Depreciation!C17 -> 2489.6093 | D16: =Capex_Depreciation!D17 -> 2725.019 | E16: =Capex_Depreciation!E17 -> 2988.1382 | F16: =Capex_Depreciation!F17 -> 3282.6398 | G16: =Capex_Depreciation!G17 -> 3612.7317 | H16: =Capex_Depreciation!H17 -> 3983.2422 | I16: =Capex_Depreciation!I17 -> 4383.7845 | ... L16: =Capex_Depreciation!L17 -> 5780.1781
A17: Change in NWC | B17: =Working_Capital!B30 -> 0 | C17: =Working_Capital!C30 -> 1500.1361 | D17: =Working_Capital!D30 -> 1678.841 | E17: =Working_Capital!E30 -> 1881.4793 | F17: =Working_Capital!F30 -> 2111.5719 | G17: =Working_Capital!G30 -> 2373.1981 | H17: =Working_Capital!H30 -> 2671.0906 | I17: =Working_Capital!I30 -> 2899.292 | ... L17: =Working_Capital!L30 -> 3658.7668
A18: FCFF | B18: =B14+B15-B16-B17 -> 18676.211 | C18: =C14+C15-C16-C17 -> 18392.388 | D18: =D14+D15-D16-D17 -> 20225.56 | E18: =E14+E15-E16-E17 -> 22282.266 | F18: =F14+F15-F16-F17 -> 24593.04 | G18: =G14+G15-G16-G17 -> 27192.987 | H18: =H14+H15-H16-H17 -> 30122.517 | I18: =I14+I15-I16-I17 -> 33414.397 | ... L18: =L14+L15-L16-L17 -> 45147.761

Sheet ROCE_Analysis
A1: ROCE Analysis
B3: FY2025A | C3: FY2026F | D3: FY2027F | E3: FY2028F | F3: FY2029F | G3: FY2030F | H3: FY2031F | I3: FY2032F | J3: FY2033F | K3: FY2034F | L3: FY2035F
A5: HUL
A6: EBIT | B6: ='Income-Statement'!B9 -> 14495.188 | C6: ='Income-Statement'!C9 -> 14822.256 | D6: ='Income-Statement'!D9 -> 15320.742 | E6: ='Income-Statement'!E9 -> 15865.683 | F6: ='Income-Statement'!F9 -> 16460.773 | G6: ='Income-Statement'!G9 -> 17110.119 | H6: ='Income-Statement'!H9 -> 17818.294 | I6: ='Income-Statement'!I9 -> 18644.294 | ... L6: ='Income-Statement'!L9 -> 21973.059
A7: Capital Employed | B7: =Balance_Sheet!B9 -> 34797 | C7: =Balance_Sheet!C9 -> 34675.443 | D7: =Balance_Sheet!D9 -> 34579.7 | E7: =Balance_Sheet!E9 -> 34507.147 | F7: =Balance_Sheet!F9 -> 34455.594 | G7: =Balance_Sheet!G9 -> 34423.22 | H7: =Balance_Sheet!H9 -> 34408.529 | I7: =Balance_Sheet!I9 -> 34403.165 | ... L7: =Balance_Sheet!L9 -> 34458.936
A8: ROCE | B8: =B6/B7 -> 0.4165643 | C8: =C6/C7 -> 0.42745687 | D8: =D6/D7 -> 0.44305595 | E8: =E6/E7 -> 0.45977962 | F8: =F6/F7 -> 0.47773876 | G8: =G6/G7 -> 0.49705167 | H8: =H6/H7 -> 0.51784527 | I8: =I6/I7 -> 0.54193542 | ... L8: =L6/L7 -> 0.63765924
A9: ROCE (Drivers) | B9: 1.082 | C9: =ROCE_Drivers!B8 -> 1.082 | D9: =ROCE_Drivers!C8 -> 1.0915752 | E9: =ROCE_Drivers!D8 -> 1.1011504 | F9: =ROCE_Drivers!E8 -> 1.1107257 | G9: =ROCE_Drivers!F8 -> 1.1203009 | H9: =ROCE_Drivers!G8 -> 1.1298761 | I9: =ROCE_Drivers!H8 -> 1.1394513 | J9: =ROCE_Drivers!I8 -> 1.1490265 | ... L9: =ROCE_Drivers!K8 -> 1.168177
A10: Difference | B10: =B8-B9 -> -0.6654357 | C10: =C8-C9 -> -0.65454313 | D10: =D8-D9 -> -0.64851927 | E10: =E8-E9 -> -0.64137082 | F10: =F8-F9 -> -0.6329869 | G10: =G8-G9 -> -0.62324922 | H10: =H8-H9 -> -0.61203083 | I10: =I8-I9 -> -0.5975159 | ... L10: =L8-L9 -> -0.53051775
A13: ITC
A14: EBIT | B14: ='Income-Statement'!B18 -> 25915.881 | C14: ='Income-Statement'!C18 -> 28314.573 | D14: ='Income-Statement'!D18 -> 31193.157 | E14: ='Income-Statement'!E18 -> 34425.748 | F14: ='Income-Statement'!F18 -> 38061.069 | G14: ='Income-Statement'!G18 -> 42155.175 | H14: ='Income-Statement'!H18 -> 46772.645 | I14: ='Income-Statement'!I18 -> 51799.704 | ... L14: ='Income-Statement'!L18 -> 69580.401
A15: Capital Employed | B15: =Balance_Sheet!B16 -> 36791.16 | C15: =Balance_Sheet!C16 -> 39634.702 | D15: =Balance_Sheet!D16 -> 42804.009 | E15: =Balance_Sheet!E16 -> 46341.054 | F15: =Balance_Sheet!F16 -> 50293.816 | G15: =Balance_Sheet!G16 -> 54717.211 | H15: =Balance_Sheet!H16 -> 59674.178 | I15: =Balance_Sheet!I16 -> 65109.56 | ... L15: =Balance_Sheet!L16 -> 84563.962
A16: ROCE | B16: =B14/B15 -> 0.7044051 | C16: =C14/C15 -> 0.71438846 | D16: =D14/D15 -> 0.72874381 | E16: =E14/E15 -> 0.74287796 | F16: =F14/F15 -> 0.75677432 | G16: =G14/G15 -> 0.77041893 | H16: =H14/H15 -> 0.78380041 | I16: =I14/I15 -> 0.79557755 | ... L16: =L14/L15 -> 0.82281387
A17: ROCE (Drivers) | B17: 0.3879 | C17: =ROCE_Drivers!B13 -> 0.3879 | D17: =ROCE_Drivers!C13 -> 0.39041883 | E17: =ROCE_Drivers!D13 -> 0.39293766 | F17: =ROCE_Drivers!E13 -> 0.39545649 | G17: =ROCE_Drivers!F13 -> 0.39797532 | H17: =ROCE_Drivers!G13 -> 0.40049416 | I17: =ROCE_Drivers!H13 -> 0.40301299 | J17: =ROCE_Drivers!I13 -> 0.40553182 | ... L17: =ROCE_Drivers!K13 -> 0.41056948
A18: Difference | B18: =B16-B17 -> 0.3165051 | C18: =C16-C17 -> 0.32648846 | D18: =D16-D17 -> 0.33832498 | E18: =E16-E17 -> 0.3499403 | F18: =F16-F17 -> 0.36131783 | G18: =G16-G17 -> 0.37244361 | H18: =H16-H17 -> 0.38330625 | I18: =I16-I17 -> 0.39256456 | ... L18: =L16-L17 -> 0.41224439

Sheet WACC
A1: WACC Assumptions
B3: HUL | C3: ITC
A5: #VALUE! | B5: {=_FV(A5,"Price")/100} -> 0.06541 | C5: =B5 -> 0.06541
A6: Equity Risk Premium | B6: 0.0726 | C6: 0.0726
A7: Beta | B7: {=TRANSPOSE(_FV(Control!B3,"Beta"))} -> 0.7473 | C7: {=_FV(Control!B4,"Beta")} -> 0.7487
A8: Cost of Equity | B8: =(B5+B7)*B6 -> 0.059002746 | C8: =(C5+C7)*C6 -> 0.059104386
A10: Pre-tax Cost of Debt | B10: =395/(1243+405) -> 0.23968447 | C10: =36.35/(1.76+37.54+117.45) -> 0.23189793
A11: After-tax Cost of Debt | B11: =B10*(1-Assumptions!$B$8) -> 0.17976335 | C11: =C10*(1-Assumptions!$B$8) -> 0.17392344
A13: Market Value of Equity | B13: {=_FV(Control!B3,"Market cap",TRUE)/10000000} -> 541016.9 | C13: {=_FV(Control!B4,"Market cap",TRUE)/10000000} -> 510367.2
A14: Market Value of Debt | B14: =1243+1+404 -> 1648 | C14: =117.45+1.76+37.54 -> 156.75
A15: Total Capital | B15: =B13+B14 -> 542664.9 | C15: =C13+C14 -> 510523.95
A16: Equity weight | B16: =B13/$B$15 -> 0.99696314 | C16: =C13/$C$15 -> 0.99969296
A17: Debt weight | B17: =B14/$B$15 -> 0.0030368649 | C17: =C14/$C$15 -> 0.00030703751
A20: WACC | B20: =Sensitivity!J4 -> 0.0597 | C20: =Sensitivity!K4 -> 0.0593

Sheet DCF_Valuation
A1: DCF Valuation
B3: FY2026F | C3: FY2027F | D3: FY2028F | E3: FY2029F | F3: FY2030F | G3: FY2031F | H3: FY2032F | I3: FY2033F | J3: FY2034F | K3: FY2035F
A5: HUL
A6: FCFF | B6: ='Cash_Flow (FCFF)'!B10 -> 10833.391 | C6: ='Cash_Flow (FCFF)'!C10 -> 11238.249 | D6: ='Cash_Flow (FCFF)'!D10 -> 11586.299 | E6: ='Cash_Flow (FCFF)'!E10 -> 11971.815 | F6: ='Cash_Flow (FCFF)'!F10 -> 12397.133 | G6: ='Cash_Flow (FCFF)'!G10 -> 12864.963 | H6: ='Cash_Flow (FCFF)'!H10 -> 13378.412 | I6: ='Cash_Flow (FCFF)'!I10 -> 13988.584 | ... K6: ='Cash_Flow (FCFF)'!K10 -> 15510.334
A7: Discount Factor | B7: =1/(1+Sensitivity!$J$4)^(COLUMN()-COLUMN($B$7)+1) -> 0.9436633 | C7: =1/(1+Sensitivity!$J$4)^(COLUMN()-COLUMN($B$7)+1) -> 0.89050043 | D7: =1/(1+Sensitivity!$J$4)^(COLUMN()-COLUMN($B$7)+1) -> 0.84033257 | E7: =1/(1+Sensitivity!$J$4)^(COLUMN()-COLUMN($B$7)+1) -> 0.79299101 | F7: =1/(1+Sensitivity!$J$4)^(COLUMN()-COLUMN($B$7)+1) -> 0.74831651 | G7: =1/(1+Sensitivity!$J$4)^(COLUMN()-COLUMN($B$7)+1) -> 0.70615883 | H7: =1/(1+Sensitivity!$J$4)^(COLUMN()-COLUMN($B$7)+1) -> 0.66637617 | I7: =1/(1+Sensitivity!$J$4)^(COLUMN()-COLUMN($B$7)+1) -> 0.62883474 | ... K7: =1/(1+Sensitivity!$J$4)^(COLUMN()-COLUMN($B$7)+1) -> 0.5599776
A8: PV of FCFF | B8: =B6*B7 -> 10223.074 | C8: =C6*C7 -> 10007.666 | D8: =D6*D7 -> 9736.3448 | E8: =E6*E7 -> 9493.5416 | F8: =F6*F7 -> 9276.9794 | G8: =G6*G7 -> 9084.7072 | H8: =H6*H7 -> 8915.0547 | I8: =I6*I7 -> 8796.5076 | ... K8: =K6*K7 -> 8685.4398
A10: ITC
A11: FCFF | B11: ='Cash_Flow (FCFF)'!B18 -> 18676.211 | C11: ='Cash_Flow (FCFF)'!C18 -> 18392.388 | D11: ='Cash_Flow (FCFF)'!D18 -> 20225.56 | E11: ='Cash_Flow (FCFF)'!E18 -> 22282.266 | F11: ='Cash_Flow (FCFF)'!F18 -> 24593.04 | G11: ='Cash_Flow (FCFF)'!G18 -> 27192.987 | H11: ='Cash_Flow (FCFF)'!H18 -> 30122.517 | I11: ='Cash_Flow (FCFF)'!I18 -> 33414.397 | ... K11: ='Cash_Flow (FCFF)'!K18 -> 40909.171
A12: Discount Factor | B12: =1/(1+Sensitivity!$K$4)^(COLUMN()-COLUMN($B$12)+1) -> 0.94401964 | C12: =1/(1+Sensitivity!$K$4)^(COLUMN()-COLUMN($B$12)+1) -> 0.89117307 | D12: =1/(1+Sensitivity!$K$4)^(COLUMN()-COLUMN($B$12)+1) -> 0.84128488 | E12: =1/(1+Sensitivity!$K$4)^(COLUMN()-COLUMN($B$12)+1) -> 0.79418944 | F12: =1/(1+Sensitivity!$K$4)^(COLUMN()-COLUMN($B$12)+1) -> 0.74973043 | G12: =1/(1+Sensitivity!$K$4)^(COLUMN()-COLUMN($B$12)+1) -> 0.70776025 | H12: =1/(1+Sensitivity!$K$4)^(COLUMN()-COLUMN($B$12)+1) -> 0.66813957 | I12: =1/(1+Sensitivity!$K$4)^(COLUMN()-COLUMN($B$12)+1) -> 0.63073687 | ... K12: =1/(1+Sensitivity!$K$4)^(COLUMN()-COLUMN($B$12)+1) -> 0.56209572
A13: PV of FCFF | B13: =B11*B12 -> 17630.709 | C13: =C11*C12 -> 16390.801 | D13: =D11*D12 -> 17015.458 | E13: =E11*E12 -> 17696.34 | F13: =F11*F12 -> 18438.15 | G13: =G11*G12 -> 19246.115 | H13: =H11*H12 -> 20126.045 | I13: =I11*I12 -> 21075.692 | ... K13: =K11*K12 -> 22994.87
B15: HUL | C15: ITC
A17: Terminal Growth | B17: =Sensitivity!J5 -> 0.03 | C17: =Sensitivity!K5 -> 0.03
A18: Terminal Value | B18: =K6*(1+B17)/(Sensitivity!J4-DCF_Valuation!B17) -> 537900.48 | C18: =K11*(1+C17)/(Sensitivity!K4-DCF_Valuation!C17) -> 1438104
A19: PV of Terminal Value | B19: =B18*K7 -> 301212.22 | C19: =C18*K12 -> 808352.08
A20: PV of FCFF | B20: =SUM(B8:K8) -> 92939.604 | C20: =SUM(B13:K13) -> 192647.4
A21: Enterprise Value | B21: =B19+B20 -> 394151.82 | C21: =C19+C20 -> 1000999.5
A22: Net Debt | B22: =WACC!B14 -> 1648 | C22: =WACC!C14 -> 156.75
A23: Equity Value | B23: =B21-B22 -> 392503.82 | C23: =C21-C22 -> 1000842.7
A24: Shares Outstanding | B24: {=_FV(Control!B3,"Shares outstanding",TRUE)/10000000} -> 234.9591 | C24: {=_FV(Control!B4,"Shares outstanding",TRUE)/10000000} -> 1252.896
A25: Intrinsic Value per share | B25: =B23/B24 -> 1670.5198 | C25: =C23/C24 -> 798.82347

Sheet Sensitivity
A1: Sensitivity - HUL (Intrinsic Value per Share)
A3: =DCF_Valuation!B25 -> 1670.5198 | B3: 0.065 | C3: 0.07 | D3: 0.075 | E3: 0.08 | F3: 0.085 | J3: HUL | K3: ITC
A4: 0.03 | B4: 1413.0893 | C4: 1232.879 | D4: 1092.808 | E4: 980.83091 | F4: 889.28245 | I4: WACC | J4: =CHOOSE(MATCH(Control!B14,{"Base","Mild","Severe","Upside"},0),Stress_Helper!F13,Stress_Helper!F14,Stress_Helper!F15,Stress_Helper!F16) -> 0.0597 | K4: =CHOOSE(MATCH(Control!B14,{"Base","Mild","Severe","Upside"},0),Stress_Helper!F21,Stress_Helper!F22,Stress_Helper!F23,Stress_Helper!F24) -> 0.0593
A5: 0.035 | B5: 1591.4352 | C5: 1361.117 | D5: 1188.4504 | E5: 1054.2151 | F5: 946.87927 | I5: Terminal g | J5: =CHOOSE(MATCH(Control!B14,{"Base","Mild","Severe","Upside"},0),Stress_Helper!G13,Stress_Helper!G14,Stress_Helper!G15,Stress_Helper!G16) -> 0.03 | K5: =CHOOSE(MATCH(Control!B14,{"Base","Mild","Severe","Upside"},0),Stress_Helper!G21,Stress_Helper!G22,Stress_Helper!G23,Stress_Helper!G24) -> 0.03
A6: 0.04 | B6: 1841.1195 | C6: 1532.1011 | D6: 1311.4191 | E6: 1145.9454 | F6: 1017.2754
A7: 0.045 | B7: 2215.6458 | C7: 1771.4787 | D7: 1475.3774 | E7: 1263.8843 | F7: 1105.2705
A8: 0.05 | B8: 2839.8565 | C8: 2130.5452 | D8: 1704.919 | E8: 1421.1361 | F8: 1218.4072
A11: Sensitivity - ITC (Intrinsic Value per Share)
A13: =DCF_Valuation!C25 -> 798.82347 | B13: 0.065 | C13: 0.07 | D13: 0.075 | E13: 0.08 | F13: 0.085
A14: 0.03 | B14: 660.83357 | C14: 572.39921 | D14: 503.79974 | E14: 449.07779 | F14: 404.44262
A15: 0.035 | B15: 749.04806 | C15: 635.82906 | D15: 551.10691 | E15: 485.37551 | F15: 432.9315
A16: 0.04 | B16: 872.54833 | C16: 720.40218 | D16: 611.93041 | E16: 530.74766 | F16: 467.75124
A17: 0.045 | B17: 1057.7987 | C17: 838.80455 | D17: 693.02842 | E17: 589.08328 | F17: 511.27591
A18: 0.05 | B18: 1366.5494 | C18: 1016.4081 | D18: 806.56563 | E18: 666.86411 | F18: 567.2362

Sheet Stress_Helper
A1: Stress Test - Intrinsic Value per Share
A3: Scenario | B3: HUL | C3: ITC
A5: Base | B5: 1670.5198 | C5: 798.82347
A6: Mild | B6: 1221.7121 | C6: 442.13593
A7: Severe | B7: 839.07412 | C7: 319.05287
A8: Upside | B8: 3389.7439 | C8: 1204.3025
A11: HUL Stress Test - Intrinsic Value per Share
A12: Scenario | B12: Rev Gr | C12: EBIT M | D12: Capex % | E12: Inv Days | F12: WACC | G12: Growth | H12: Intrinsic Value
A13: Base | B13: 0.022563928 | C13: 0.226 | D13: 0.019551592 | E13: 50.553563 | F13: 0.0597 | G13: 0.03 | H13: 1670.5198
A14: Mild | B14: =B13-0.005 -> 0.017563928 | C14: =C13-0.01 -> 0.216 | D14: =D13+0.005 -> 0.024551592 | E14: =E13+4.45 -> 55.003563 | F14: =F13+0.5% -> 0.0647 | G14: =G13-0.5% -> 0.025 | H14: 1221.7121
A15: Severe | B15: =B13-0.01 -> 0.012563928 | C15: =C13-0.03 -> 0.196 | D15: =D13+0.01 -> 0.029551592 | E15: =E13+9.45 -> 60.003563 | F15: =F13+1% -> 0.0697 | G15: =G13-1% -> 0.02 | H15: 839.07412
A16: Upside | B16: =B13+0.005 -> 0.027563928 | C16: =C13+0.02 -> 0.246 | D16: =D13-0.3% -> 0.016551592 | E16: =E13-5 -> 45.553563 | F16: =F13-0.5% -> 0.0547 | G16: 0.04 | H16: 3389.7439
A19: ITC Stress Test - Intrinsic Value per Share
A20: Scenario | B20: Rev Gr | C20: EBIT M | D20: Capex % | E20: Inv Days | F20: WACC | G20: Growth | H20: Intrinsic Value
A21: Base | B21: 0.092556862 | C21: 0.308 | D21: 0.027081449 | E21: 174.51472 | F21: 0.0593 | G21: 0.03 | H21: 798.82347
A22: Mild | B22: 0.072556862 | C22: 0.298 | D22: 0.032081449 | E22: 184.51472 | F22: 0.0643 | G22: 0.025 | H22: 442.13593
A23: Severe | B23: 0.049956862 | C23: 0.278 | D23: 0.037081449 | E23: 194.51472 | F23: 0.0693 | G23: 0.02 | H23: 319.05287
A24: Upside | B24: 0.11255686 | C24: 0.328 | D24: 0.024081449 | E24: 164.51472 | F24: 0.0543 | G24: 0.04 | H24: 1204.3025

Sheet Output_Dashboard
A1: FMCG ROCE Compounding Dashboard | I1: Scenario | J1: =Control!B14 -> Base
A2: #VALUE!
A4: HUL-Business Snapshot | B4: HUL | C4: ITC | H4: Valuation Summary | I4: HUL | J4: ITC
A5: ROCE | B5: =ROCE_Analysis!C8 -> 0.42745687 | C5: =ROCE_Analysis!C16 -> 0.71438846 | H5: Enterprise Value | I5: =DCF_Valuation!B21 -> 394151.82 | J5: =DCF_Valuation!C21 -> 1000999.5
A6: EBIT Margin | B6: =Operating_Margins!C9 -> 0.226 | C6: =Operating_Margins!C18 -> 0.308 | H6: Equity Value | I6: =DCF_Valuation!B23 -> 392503.82 | J6: =DCF_Valuation!C23 -> 1000842.7
A7: Revenue Growth | B7: =Revenue_Drivers!C7 -> 0.024563928 | C7: =Revenue_Drivers!C12 -> 0.094556862 | H7: Intrinsic Value/Share | I7: =DCF_Valuation!B25 -> 1670.5198 | J7: =DCF_Valuation!C25 -> 798.82347
A8: Capital Turnover | B8: =ROCE_Drivers!B7 -> 4.7876106 | C8: =ROCE_Drivers!B12 -> 1.2594156 | H8: Current Market Price | I8: {=_FV(Control!B3,"Price")} -> 2282.2 | J8: {=_FV(Control!B4,"Price")} -> 406.6
A9: WACC | B9: =WACC!B20 -> 0.0597 | C9: =WACC!C20 -> 0.0593 | H9: Upside/Downside | I9: =(I7/I8)-1 -> -0.26802218 | J9: =(J7/J8)-1 -> 0.96464208
A12: HUL Trends
A13: Year | B13: ROCE | C13: FCFF
A14: {=TRANSPOSE(DCF_Valuation!B3:K3)} -> FY2026F | B14: {=TRANSPOSE(ROCE_Analysis!C8:L8)} -> 0.42745687 | C14: {=TRANSPOSE(DCF_Valuation!B6:K6)} -> 10833.391
A15: FY2027F | B15: 0.44305595 | C15: 11238.249
A16: FY2028F | B16: 0.45977962 | C16: 11586.299
A17: FY2029F | B17: 0.47773876 | C17: 11971.815
A18: FY2030F | B18: 0.49705167 | C18: 12397.133
A19: FY2031F | B19: 0.51784527 | C19: 12864.963
A20: FY2032F | B20: 0.54193542 | C20: 13378.412
A21: FY2033F | B21: 0.56965674 | C21: 13988.584
A22: FY2034F | B22: 0.60140769 | C22: 14695.262
A23: FY2035F | B23: 0.63765924 | C23: 15510.334
A25: ITC Trends
A26: Year | B26: ROCE | C26: FCFF
A27: FY2026F | B27: {=TRANSPOSE(ROCE_Analysis!C16:L16)} -> 0.71438846 | C27: {=TRANSPOSE(DCF_Valuation!B11:K11)} -> 18676.211
A28: FY2027F | B28: 0.72874381 | C28: 18392.388
A29: FY2028F | B29: 0.74287796 | C29: 20225.56
A30: FY2029F | B30: 0.75677432 | C30: 22282.266
A31: FY2030F | B31: 0.77041893 | C31: 24593.04
A32: FY2031F | B32: 0.78380041 | C32: 27192.987
A33: FY2032F | B33: 0.79557755 | C33: 30122.517
A34: FY2033F | B34: 0.80590825 | C34: 33414.397
A35: FY2034F | B35: 0.81494119 | C35: 37004.005
A36: FY2035F | B36: 0.82281387 | C36: 40909.171
F38: "All figures in INR Cr unless stated. Scenario-driven forecasts."

Sheet Checks
A1: Model Checks - FMCG ROCE Compounding Model
A3: Check Category | B3: HUL | C3: ITC | D3: Status
A5: EBIT Reconcilliation | B5: ='Income-Statement'!C9-Operating_Margins!C10 -> 0 | C5: ='Income-Statement'!C18-Operating_Margins!C19 -> 0 | D5: =IF(AND(ABS(B5)<0.01,ABS(C5)<0.01),"OK","Check") -> OK
A6: FCFF Consistency | B6: ='Cash_Flow (FCFF)'!C10-('Income-Statement'!C11+Capex_Depreciation!C10-Capex_Depreciation!C8-Working_Capital!C16) -> 0 | C6: ='Cash_Flow (FCFF)'!C18-('Income-Statement'!C20+Capex_Depreciation!C19-Capex_Depreciation!C17-Working_Capital!C30) -> 0 | D6: =IF(AND(ABS(B6)<0.01,ABS(C6)<0.01),"OK","Check") -> OK
A7: PPE Roll-forward | B7: =Capex_Depreciation!C11-(Capex_Depreciation!B11+Capex_Depreciation!C8-Capex_Depreciation!C10) -> 0 | C7: =Capex_Depreciation!C20-(Capex_Depreciation!B20+Capex_Depreciation!C17-Capex_Depreciation!C19) -> 0 | D7: =IF(AND(ABS(B7)<0.01,ABS(C7)<0.01),"OK","Check") -> OK
A8: Working Capital Flow | B8: =Working_Capital!C16-(Working_Capital!C15-Working_Capital!B15) -> 0 | C8: =Working_Capital!C30-(Working_Capital!C29-Working_Capital!B29) -> 0 | D8: =IF(AND(ABS(B8)<0.01,ABS(C8)<0.01),"OK","Check") -> OK
A9: ROCE Sanity | B9: =ROCE_Analysis!C8-'Income-Statement'!C9/Balance_Sheet!C9 -> 0 | C9: =ROCE_Analysis!C16-'Income-Statement'!C18/Balance_Sheet!C16 -> 0 | D9: =IF(AND(ABS(B9)<0.01,ABS(C9)<0.01),"OK","Check") -> OK
A10: Growth vs Reinvestment | B10: =Revenue_Drivers!C7-ROCE_Analysis!C8*((Capex_Depreciation!C8+Working_Capital!C16)/'Income-Statement'!C11) -> -0.020977719 | C10: =Revenue_Drivers!C12-ROCE_Analysis!C16*((Capex_Depreciation!C17+Working_Capital!C30)/'Income-Statement'!C20) -> -0.039660384 | D10: =IF(AND(ABS(B10)<0.05,ABS(C10)<0.05),"OK","Check") -> OK
A11: DCF Discounting | B11: =DCF_Valuation!B8-DCF_Valuation!B6*DCF_Valuation!B7 -> 0 | C11: =DCF_Valuation!B13-DCF_Valuation!B11*DCF_Valuation!B12 -> 0 | D11: =IF(AND(ABS(B11)<0.01,ABS(C11)<0.01),"OK","Check") -> OK
A12: Terminal Value Share | B12: =DCF_Valuation!B19/DCF_Valuation!B21 -> 0.76420354 | C12: =DCF_Valuation!C19/DCF_Valuation!C21 -> 0.80754495 | D12: =IF(AND(ABS(B12)<0.85,ABS(C12)<0.85),"OK","Check") -> OK
A13: Equity Bridge | B13: =DCF_Valuation!B23-(DCF_Valuation!B21-DCF_Valuation!B22) -> 0 | C13: =DCF_Valuation!C23-(DCF_Valuation!C21-DCF_Valuation!C22) -> 0 | D13: =IF(AND(ABS(B13)<0.01,ABS(C13)<0.01),"OK","Check") -> OK
A14: No Circulars / Errors | B14: =IF(COUNTIF(ModelRange,"#*")=0,0,1) -> 0 | C14: =IF(COUNTIF(ModelRange,"#*")=0,0,1) -> 0 | D14: =IF(AND(ABS(B14)<0.01,ABS(C14)<0.01),"OK","Check") -> OK
