Workbook

Sheet Cover
A1: #VALUE!
A3: LBO + DCF Returns Framework
A4: An capital structure & valuation model
A6: Case Company | B6: #VALUE!
A9: Built by: Akshat Gupta | Aurex Research
A12: Version: v1.0 | B12: Date: | C12: =TODAY() -> 46018
A15: For educational and analytical purposes only. Not an investment recommendation.

Sheet Control Panel
A1: Control Panel
A2: All figures in Rs Cr unless stated
A4: Scenario | B4: Base
A6: Operating Scenario Inputs
A8: Revenue Growth | B8: =CHOOSE(MATCH(B4,{"Base","Upside","Downside"},0),'Scenario Assumptions'!B6,'Scenario Assumptions'!C6,'Scenario Assumptions'!D6) -> 0.2415
A9: EBITDA Margin | B9: =CHOOSE(MATCH(B4,{"Base","Upside","Downside"},0),'Scenario Assumptions'!B7,'Scenario Assumptions'!C7,'Scenario Assumptions'!D7) -> 0.1725
A10: Capex % of Revenue | B10: =CHOOSE(MATCH(B4,{"Base","Upside","Downside"},0),'Scenario Assumptions'!B8,'Scenario Assumptions'!C8,'Scenario Assumptions'!D8) -> 0.04
A11: Depreciation % of Revenue | B11: =Capex_Depreciation!B8/Capex_Depreciation!B5 -> 0.055662588
A12: WC as % of Revenue | B12: =CHOOSE(MATCH(B4,{"Base","Upside","Downside"},0),'Scenario Assumptions'!B10,'Scenario Assumptions'!C10,'Scenario Assumptions'!D10) -> 0.09685
A13: Cost of Debt | B13: =CHOOSE(MATCH(B4,{"Base","Upside","Downside"},0),'Scenario Assumptions'!B9,'Scenario Assumptions'!C9,'Scenario Assumptions'!D9) -> 0.11
A14: Tax Rate | B14: 0.25
A16: Valuation & Deal Inputs
A18: WACC | B18: =CHOOSE(MATCH(B4,{"Base","Upside","Downside"},0),'Scenario Assumptions'!B15,'Scenario Assumptions'!C15,'Scenario Assumptions'!D15) -> 0.1412327
A19: Terminal Growth | B19: =CHOOSE(MATCH(B4,{"Base","Upside","Downside"},0),'Scenario Assumptions'!B16,'Scenario Assumptions'!C16,'Scenario Assumptions'!D16) -> 0.035
A20: Entry EV/EBITDA | B20: =CHOOSE(MATCH(B4,{"Base","Upside","Downside"},0),'Scenario Assumptions'!B21,'Scenario Assumptions'!C21,'Scenario Assumptions'!D21) -> 24.95
A21: Exit EV/EBITDA | B21: =CHOOSE(MATCH(B4,{"Base","Upside","Downside"},0),'Scenario Assumptions'!B25,'Scenario Assumptions'!C25,'Scenario Assumptions'!D25) -> 24.95
A22: Holding Period (Years)
A23: Target Debt % of EV | B23: =CHOOSE(MATCH(B4,{"Base","Upside","Downside"},0),'Scenario Assumptions'!B22,'Scenario Assumptions'!C22,'Scenario Assumptions'!D22) -> 0.5
A25: Key Outputs Snapshot
A27: Intrinsic EV (DCF)
A28: Entry EV | B28: =B20*(1296.1+134.7+427.6) -> 46367.08
A29: Equity Invested | B29: =(B28*0.02)+B28-(B28*B23)-7956 -> 16154.882
A30: Exit Equity Value
A31: Equity IRR
A32: MOIC
A33: Fee % of EV | B33: 0.02

Sheet Scenario Assumptions
A1: Scenario Assumptions
A4: Operating Drivers
A5: Assumption | B5: Base | C5: Upside | D5: Downside
A6: Revenue Growth | B6: 0.2415 | C6: 0.2815 | D6: 0.2015
A7: EBITDA Margin | B7: 0.1725 | C7: 0.1925 | D7: 0.1525
A8: Capex % of Revenue | B8: 0.04 | C8: 0.03 | D8: 0.05
A9: Cost of Debt | B9: 0.11 | C9: 0.08 | D9: 0.15
A10: WC % of Revenue | B10: 0.09685 | C10: 0.07685 | D10: 0.11685
A13: Valuation Drivers
A14: Assumption | B14: Base | C14: Upside | D14: Downside
A15: WACC | B15: =WACC!B15 -> 0.1412327 | C15: 0.1 | D15: 0.15
A16: Terminal Growth | B16: 0.035 | C16: 0.045 | D16: 0.025
A19: Transaction / LBO Drivers
A20: Assumption | B20: Base | C20: Upside | D20: Downside
A21: Entry EV/EBITDA | B21: 24.95 | C21: 25.95 | D21: 23.95
A22: Target Debt % of EV | B22: 0.5 | C22: 0.55 | D22: 0.45
A23: Fees % of EV | B23: 0.02 | C23: 0.02 | D23: 0.02
A24: Holding Period | B24: 3 | C24: 4 | D24: 5
A25: Exit EV/EBITDA | B25: =IRR_Sensitivity!J6 -> 24.95 | C25: =B25+1 -> 25.95 | D25: =B25-1 -> 23.95

Sheet Operating Drivers
A1: Operating Drivers
A2: All figures in Rs Cr unless stated
A4: Particulars | B4: FY2025A | C4: FY2026E | D4: FY2027E | E4: FY2028E | F4: FY2029E | G4: FY2030E
A5: Revenue
A6: Revenue | B6: 12050.7 | C6: =B6*(1+C7) -> 15201.958 | D6: =C6*(1+D7) -> 18417.172 | E6: =D6*(1+E7) -> 21391.545 | F6: =E6*(1+F7) -> 24204.534 | G6: =F6*(1+G7) -> 27871.521
A7: Revenue Growth % | B7: ='Control Panel'!B8 -> 0.2415 | C7: =B7+0.02 -> 0.2615 | D7: =C7-0.05 -> 0.2115 | E7: =D7-0.05 -> 0.1615 | F7: =E7-0.03 -> 0.1315 | G7: =F7+0.02 -> 0.1515
A8: EBITDA
A9: EBITDA Margin | B9: ='Control Panel'!B9 -> 0.1725 | C9: =B9+0.01 -> 0.1825 | D9: =C9+0.01 -> 0.1925 | E9: =D9+0.01 -> 0.2025 | F9: =E9 -> 0.2025 | G9: =F9+0.0025 -> 0.205
A10: EBITDA | B10: =B6*B9 -> 2078.7458 | C10: =C6*C9 -> 2774.3573 | D10: =D6*D9 -> 3545.3056 | E10: =E6*E9 -> 4331.788 | F10: =F6*F9 -> 4901.4181 | G10: =G6*G9 -> 5713.6617
A11: Capex
A12: Capex % of Revenue | B12: ='Control Panel'!B10 -> 0.04 | C12: =B12+0.01 -> 0.05 | D12: =C12 -> 0.05 | E12: =D12 -> 0.05 | F12: =E12 -> 0.05 | G12: =F12 -> 0.05
A13: Capex | B13: =B6*B12 -> 482.028 | C13: =C6*C12 -> 760.0979 | D13: =D6*D12 -> 920.85861 | E13: =E6*E12 -> 1069.5773 | F13: =F6*F12 -> 1210.2267 | G13: =G6*G12 -> 1393.576
A14: Working Capital
A15: WC % of Revenue | B15: ='Control Panel'!B12 -> 0.09685 | C15: =B15 -> 0.09685 | D15: =C15 -> 0.09685 | E15: =D15 -> 0.09685 | F15: =E15 -> 0.09685 | G15: =F15 -> 0.09685
A16: Working Capital | B16: =B6*B15 -> 1167.1103 | C16: =C6*C15 -> 1472.3096 | D16: =D6*D15 -> 1783.7031 | E16: =E6*E15 -> 2071.7712 | F16: =F6*F15 -> 2344.2091 | G16: =G6*G15 -> 2699.3568
A17: Change in WC | B17: 0 | C17: =C16-B16 -> 305.19934 | D17: =D16-C16 -> 311.39349 | E17: =E16-D16 -> 288.06805 | F17: =F16-E16 -> 272.43791 | G17: =G16-F16 -> 355.14768
A18: Cash Proxy
A19: Cash Proxy | C19: =C10-C13-C17 -> 1709.0601 | D19: =D10-D13-D17 -> 2313.0535 | E19: =E10-E13-E17 -> 2974.1426 | F19: =F10-F13-F17 -> 3418.7535 | G19: =G10-G13-G17 -> 3964.938

Sheet Capex_Depreciation
A1: Capex & Depreciation
A2: All figures in Rs Cr unless stated
A4: Particulars | B4: FY2025A | C4: FY2026E | D4: FY2027E | E4: FY2028E | F4: FY2029E | G4: FY2030E
A5: Opening Net PPE | B5: 7682 | C5: =B9 -> 7736.428 | D5: =C9 -> 8065.8963 | E5: =D9 -> 8537.7862 | F5: =E9 -> 9132.1282 | G5: =F9 -> 9834.037
A7: Capex | B7: ='Operating Drivers'!B13 -> 482.028 | C7: ='Operating Drivers'!C13 -> 760.0979 | D7: ='Operating Drivers'!D13 -> 920.85861 | E7: ='Operating Drivers'!E13 -> 1069.5773 | F7: ='Operating Drivers'!F13 -> 1210.2267 | G7: ='Operating Drivers'!G13 -> 1393.576
A8: Depreciation | B8: 427.6 | C8: =C5*'Control Panel'!$B$11 -> 430.6296 | D8: =D5*'Control Panel'!$B$11 -> 448.96866 | E8: =E5*'Control Panel'!$B$11 -> 475.23528 | F8: =F5*'Control Panel'!$B$11 -> 508.31789 | G8: =G5*'Control Panel'!$B$11 -> 547.38795
A9: Closing Net PPE | B9: =B5+B7-B8 -> 7736.428 | C9: =C5+C7-C8 -> 8065.8963 | D9: =D5+D7-D8 -> 8537.7862 | E9: =E5+E7-E8 -> 9132.1282 | F9: =F5+F7-F8 -> 9834.037 | G9: =G5+G7-G8 -> 10680.225

Sheet Debt_Interest
A1: Debt & Interest Schedule
A2: All figures in Rs Cr unless stated
A4: Rs Crores | B4: FY2025A | C4: FY2026E | D4: FY2027E | E4: FY2028E | F4: FY2029E | G4: FY2030E
A5: Opening Debt | B5: =3399+967 -> 4366 | C5: =B12 -> 7005 | D5: =C12 -> 0 | E5: =D12 -> 0 | F5: =E12 -> 0 | G5: =F12 -> 0
A6: New Borrowings | B6: 6039 | C6: 0 | D6: 0 | E6: 0 | F6: 0 | G6: 0
A7: Interest Rate | B7: 0.11 | C7: =B7 -> 0.11 | D7: =C7 -> 0.11 | E7: =D7 -> 0.11 | F7: =E7 -> 0.11 | G7: =F7 -> 0.11
A9: Interest Expense | B9: =B7*AVERAGE(B5,B6) -> 572.275 | C9: =C7*AVERAGE(C5,C6) -> 385.275 | D9: =D7*AVERAGE(D5,D6) -> 0 | E9: =E7*AVERAGE(E5,E6) -> 0 | F9: =F7*AVERAGE(F5,F6) -> 0 | G9: =G7*AVERAGE(G5,G6) -> 0
A10: Cash Available for Debt Repayment | B10: =Cash_Flow!B19 -> 6254.4617 | C10: =Cash_Flow!C19 -> 8223.5544 | D10: =Cash_Flow!D19 -> 11604.241 | E10: =Cash_Flow!E19 -> 15753.4 | F10: =Cash_Flow!F19 -> 20494.332 | G10: =Cash_Flow!G19 -> 25954.853
A11: Debt Repayment | B11: =B5+B6-7005 -> 3400 | C11: =MIN(C10,C5+C6) -> 7005 | D11: =MIN(D10,D5+D6) -> 0 | E11: =MIN(E10,E5+E6) -> 0 | F11: =MIN(F10,F5+F6) -> 0 | G11: =MIN(G10,G5+G6) -> 0
A12: Closing Debt | B12: =B5+B6-B11 -> 7005 | C12: =C5+C6-C11 -> 0 | D12: =D5+D6-D11 -> 0 | E12: =E5+E6-E11 -> 0 | F12: =F5+F6-F11 -> 0 | G12: =G5+G6-G11 -> 0

Sheet Income_Statement
A1: Income Statement
A2: All figures in Rs Cr unless stated
A4: Particulars | B4: FY2025A | C4: FY2026E | D4: FY2027E | E4: FY2028E | F4: FY2029E | G4: FY2030E
A5: Revenue & EBITDA
A6: Revenue | B6: ='Operating Drivers'!B6 -> 12050.7 | C6: ='Operating Drivers'!C6 -> 15201.958 | D6: ='Operating Drivers'!D6 -> 18417.172 | E6: ='Operating Drivers'!E6 -> 21391.545 | F6: ='Operating Drivers'!F6 -> 24204.534 | G6: ='Operating Drivers'!G6 -> 27871.521
A8: EBITDA | B8: ='Operating Drivers'!B10 -> 2078.7458 | C8: ='Operating Drivers'!C10 -> 2774.3573 | D8: ='Operating Drivers'!D10 -> 3545.3056 | E8: ='Operating Drivers'!E10 -> 4331.788 | F8: ='Operating Drivers'!F10 -> 4901.4181 | G8: ='Operating Drivers'!G10 -> 5713.6617
A9: Depreciation | B9: =Capex_Depreciation!B8 -> 427.6 | C9: =Capex_Depreciation!C8 -> 430.6296 | D9: =Capex_Depreciation!D8 -> 448.96866 | E9: =Capex_Depreciation!E8 -> 475.23528 | F9: =Capex_Depreciation!F8 -> 508.31789 | G9: =Capex_Depreciation!G8 -> 547.38795
A11: EBIT | B11: =B8-B9 -> 1651.1458 | C11: =C8-C9 -> 2343.7277 | D11: =D8-D9 -> 3096.337 | E11: =E8-E9 -> 3856.5527 | F11: =F8-F9 -> 4393.1002 | G11: =G8-G9 -> 5166.2738
A13: Interest Expense | B13: =Debt_Interest!B9 -> 572.275 | C13: =Debt_Interest!C9 -> 385.275 | D13: =Debt_Interest!D9 -> 0 | E13: =Debt_Interest!E9 -> 0 | F13: =Debt_Interest!F9 -> 0 | G13: =Debt_Interest!G9 -> 0
A15: EBT | B15: =B11-B13 -> 1078.8708 | C15: =C11-C13 -> 1958.4527 | D15: =D11-D13 -> 3096.337 | E15: =E11-E13 -> 3856.5527 | F15: =F11-F13 -> 4393.1002 | G15: =G11-G13 -> 5166.2738
A17: Taxes | B17: =B15*'Control Panel'!$B$14 -> 269.71769 | C17: =C15*'Control Panel'!$B$14 -> 489.61319 | D17: =D15*'Control Panel'!$B$14 -> 774.08425 | E17: =E15*'Control Panel'!$B$14 -> 964.13817 | F17: =F15*'Control Panel'!$B$14 -> 1098.275 | G17: =G15*'Control Panel'!$B$14 -> 1291.5684
A19: Net Income | B19: =B15-B17 -> 809.15306 | C19: =C15-C17 -> 1468.8396 | D19: =D15-D17 -> 2322.2527 | E19: =E15-E17 -> 2892.4145 | F19: =F15-F17 -> 3294.8251 | G19: =G15-G17 -> 3874.7053

Sheet Balance_Sheet
A1: Balance Sheet
A2: All figures in Rs Cr unless stated
A4: Particulars | B4: FY2025A | C4: FY2026E | D4: FY2027E | E4: FY2028E | F4: FY2029E | G4: FY2030E
A5: ASSETS
A6: Current Assets
A7: Cash | B7: =B23-(B8+B12+B13+B14) -> 6254.4617 | C7: =C23-(C8+C12+C13+C14) -> -576.05287 | D7: =D23-(D8+D12+D13+D14) -> 109.50325 | E7: =E23-(E8+E12+E13+E14) -> 1549.3459 | F7: =F23-(F8+F12+F13+F14) -> 3467.4137 | G7: =G23-(G8+G12+G13+G14) -> 5560.9031
A8: Net Working Capital | B8: ='Operating Drivers'!B16 -> 1167.1103 | C8: ='Operating Drivers'!C16 -> 1472.3096 | D8: ='Operating Drivers'!D16 -> 1783.7031 | E8: ='Operating Drivers'!E16 -> 2071.7712 | F8: ='Operating Drivers'!F16 -> 2344.2091 | G8: ='Operating Drivers'!G16 -> 2699.3568
A9: Total Current Assets | B9: =SUM(B7:B8) -> 7421.572 | C9: =SUM(C7:C8) -> 896.25676 | D9: =SUM(D7:D8) -> 1893.2064 | E9: =SUM(E7:E8) -> 3621.1171 | F9: =SUM(F7:F8) -> 5811.6228 | G9: =SUM(G7:G8) -> 8260.2599
A11: Non-current Assets
A12: Net PPE | B12: =Capex_Depreciation!B9 -> 7736.428 | C12: =Capex_Depreciation!C9 -> 8065.8963 | D12: =Capex_Depreciation!D9 -> 8537.7862 | E12: =Capex_Depreciation!E9 -> 9132.1282 | F12: =Capex_Depreciation!F9 -> 9834.037 | G12: =Capex_Depreciation!G9 -> 10680.225
A13: Other Assets | B13: 5913 | C13: 5913 | D13: 5913 | E13: 5913 | F13: 5913 | G13: 5913
A14: Other Intangible Assets | B14: =38430+11296 -> 49726 | C14: =38430+11296 -> 49726 | D14: =38430+11296 -> 49726 | E14: =38430+11296 -> 49726 | F14: =38430+11296 -> 49726 | G14: =38430+11296 -> 49726
A15: Total Non-current assets | B15: =SUM(B12:B14) -> 63375.428 | C15: =SUM(C12:C14) -> 63704.896 | D15: =SUM(D12:D14) -> 64176.786 | E15: =SUM(E12:E14) -> 64771.128 | F15: =SUM(F12:F14) -> 65473.037 | G15: =SUM(G12:G14) -> 66319.225
A16: Total Assets | B16: =B9+B15 -> 70797 | C16: =C9+C15 -> 64601.153 | D16: =D9+D15 -> 66069.993 | E16: =E9+E15 -> 68392.245 | F16: =F9+F15 -> 71284.66 | G16: =G9+G15 -> 74579.485
A18: Long-term Debt | B18: =Debt_Interest!B12 -> 7005 | C18: =Debt_Interest!C12 -> 0 | D18: =Debt_Interest!D12 -> 0 | E18: =Debt_Interest!E12 -> 0 | F18: =Debt_Interest!F12 -> 0 | G18: =Debt_Interest!G12 -> 0
A19: Total Liabilities | B19: =SUM(B18:B18) -> 7005 | C19: =SUM(C18:C18) -> 0 | D19: =SUM(D18:D18) -> 0 | E19: =SUM(E18:E18) -> 0 | F19: =SUM(F18:F18) -> 0 | G19: =SUM(G18:G18) -> 0
A21: Share Capital | B21: 669 | C21: 669 | D21: 669 | E21: 669 | F21: 669 | G21: 669
A22: Retained Earnings | B22: 63123 | C22: =B22+Income_Statement!B19 -> 63932.153 | D22: =C22+Income_Statement!C19 -> 65400.993 | E22: =D22+Income_Statement!D19 -> 67723.245 | F22: =E22+Income_Statement!E19 -> 70615.66 | G22: =F22+Income_Statement!F19 -> 73910.485
A23: Total Equity & Liabilities | B23: =B19+B21+B22 -> 70797 | C23: =C19+C21+C22 -> 64601.153 | D23: =D19+D21+D22 -> 66069.993 | E23: =E19+E21+E22 -> 68392.245 | F23: =F19+F21+F22 -> 71284.66 | G23: =G19+G21+G22 -> 74579.485

Sheet Cash_Flow
A1: Cash Flow Statement
A2: All figures in Rs Cr unless stated
A4: Particulars | B4: FY2025A | C4: FY2026E | D4: FY2027E | E4: FY2028E | F4: FY2029E | G4: FY2030E
A5: Operating Activities
A6: Net Income | B6: =Income_Statement!B19 -> 809.15306 | C6: =Income_Statement!C19 -> 1468.8396 | D6: =Income_Statement!D19 -> 2322.2527 | E6: =Income_Statement!E19 -> 2892.4145 | F6: =Income_Statement!F19 -> 3294.8251 | G6: =Income_Statement!G19 -> 3874.7053
A7: Depreciation | B7: =Income_Statement!B9 -> 427.6 | C7: =Income_Statement!C9 -> 430.6296 | D7: =Income_Statement!D9 -> 448.96866 | E7: =Income_Statement!E9 -> 475.23528 | F7: =Income_Statement!F9 -> 508.31789 | G7: =Income_Statement!G9 -> 547.38795
A8: Change in Working Capital | B8: ='Operating Drivers'!B17 -> 0 | C8: ='Operating Drivers'!C17 -> 305.19934 | D8: ='Operating Drivers'!D17 -> 311.39349 | E8: ='Operating Drivers'!E17 -> 288.06805 | F8: ='Operating Drivers'!F17 -> 272.43791 | G8: ='Operating Drivers'!G17 -> 355.14768
A9: Cash flow from Operations | B9: =B6+B7-B8 -> 1236.7531 | C9: =C6+C7-C8 -> 1594.2698 | D9: =D6+D7-D8 -> 2459.8279 | E9: =E6+E7-E8 -> 3079.5817 | F9: =F6+F7-F8 -> 3530.7051 | G9: =G6+G7-G8 -> 4066.9456
A10: Investing Activities
A11: Capex | B11: =Capex_Depreciation!B7 -> 482.028 | C11: =Capex_Depreciation!C7 -> 760.0979 | D11: =Capex_Depreciation!D7 -> 920.85861 | E11: =Capex_Depreciation!E7 -> 1069.5773 | F11: =Capex_Depreciation!F7 -> 1210.2267 | G11: =Capex_Depreciation!G7 -> 1393.576
A12: Cash flow from Investing | B12: =B11 -> 482.028 | C12: =C11 -> 760.0979 | D12: =D11 -> 920.85861 | E12: =E11 -> 1069.5773 | F12: =F11 -> 1210.2267 | G12: =G11 -> 1393.576
A13: Financing Activities
A14: Interest Paid | B14: =Debt_Interest!B9 -> 572.275 | C14: =Debt_Interest!C9 -> 385.275 | D14: =Debt_Interest!D9 -> 0 | E14: =Debt_Interest!E9 -> 0 | F14: =Debt_Interest!F9 -> 0 | G14: =Debt_Interest!G9 -> 0
A15: Debt Repayment
A16: Cash flow from Financing Activities | B16: =-B14-B15 -> -572.275 | C16: =-C14-C15 -> -385.275 | D16: =-D14-D15 -> 0 | E16: =-E14-E15 -> 0 | F16: =-F14-F15 -> 0 | G16: =-G14-G15 -> 0
A17: Net Cash | B17: =B9+B12+B16 -> 1146.5061 | C17: =C9+C12+C16 -> 1969.0927 | D17: =D9+D12+D16 -> 3380.6865 | E17: =E9+E12+E16 -> 4149.159 | F17: =F9+F12+F16 -> 4740.9318 | G17: =G9+G12+G16 -> 5460.5216
A18: Opening Cash | B18: 3213 | C18: =B19 -> 6254.4617 | D18: =C19 -> 8223.5544 | E18: =D19 -> 11604.241 | F18: =E19 -> 15753.4 | G18: =F19 -> 20494.332
A19: Closing Cash | B19: =Balance_Sheet!B7 -> 6254.4617 | C19: =C17+C18 -> 8223.5544 | D19: =D17+D18 -> 11604.241 | E19: =E17+E18 -> 15753.4 | F19: =F17+F18 -> 20494.332 | G19: =G17+G18 -> 25954.853

Sheet WACC
A1: WACC
A3: Market Assumptions | E3: Capital Structure
A4: Risk-Free Rate | B4: 0.066 | E4: Market value of Equity | F4: {=_FV(Cover!B6,"Market cap",TRUE)/10000000} -> 58220.21
A5: Equity Risk Premium | B5: 0.0726 | E5: Market value of Debt | F5: =Balance_Sheet!B18 -> 7005
A6: Beta | B6: {=_FV(Cover!B6,"Beta")} -> 1.1336 | E6: Total Capital | F6: =F4+F5 -> 65225.21
A7: Cost of Equity | B7: =B4+B5*B6 -> 0.14829936 | E7: Weight of Equity | F7: =F4/$F$6 -> 0.89260288
E8: Weight of Debt | F8: =F5/$F$6 -> 0.10739712
A9: Cost of Debt
A10: Pre-Tax Cost of Debt | B10: ='Control Panel'!B13 -> 0.11
A11: Tax rate | B11: ='Control Panel'!B14 -> 0.25 | E11: WACC Breakdown
A12: After-tax Cost of Debt | B12: =B10*(1-B11) -> 0.0825 | E12: Component | F12: Value
E13: Cost of Equity | F13: =B7 -> 0.14829936
A14: WACC Summary | E14: After-tax Cost of Debt | F14: =B12 -> 0.0825
A15: WACC | B15: =(B7*F7)+(B12*F8) -> 0.1412327 | E15: Equity Weight | F15: =F7 -> 0.89260288
E16: Debt Weight | F16: =F8 -> 0.10739712
E17: WACC | F17: ='Control Panel'!B18 -> 0.1412327

Sheet DCF_Valuation
A1: DCF Valuation - FCFF Based
A2: All figures in Rs Cr unless stated
A4: Assumptions Box | H4: Valuation Summary Box
A5: WACC | B5: =WACC!B15 -> 0.1412327 | H5: Enterprise Value | I5: =B16+B23 -> 19468.417
A6: Terminal g | B6: ='Control Panel'!B19 -> 0.035 | H6: Less: Net Debt | I6: =Balance_Sheet!B18-Balance_Sheet!B7 -> 750.53829
A7: Forecast Years | B7: 5 | H7: Equity Value | I7: =I5-I6 -> 18717.879
A8: Valuation Year | B8: FY2026E | H8: Shares Outstanding | I8: {=_FV(Cover!B6,"Shares outstanding",TRUE)/10000000} -> 33.50418
H9: Intrinsic Value / Share | I9: =I7/I8 -> 558.67295
H10: Current Market Price | I10: {=_FV(Cover!B6,"Price")} -> 1673.3
A11: FCFF & PV Table | H11: Upside / (Downside) | I11: =(I9/I10)-1 -> -0.66612505
A12: Particulars | B12: FY2026E | C12: FY2027E | D12: FY2028E | E12: FY2029E | F12: FY2030E
A13: Free Cash Flow to Firm (FCFF) | B13: =Cash_Flow!C6+Cash_Flow!C7-Cash_Flow!C8-Cash_Flow!C11 -> 834.17191 | C13: =Cash_Flow!D6+Cash_Flow!D7-Cash_Flow!D8-Cash_Flow!D11 -> 1538.9693 | D13: =Cash_Flow!E6+Cash_Flow!E7-Cash_Flow!E8-Cash_Flow!E11 -> 2010.0045 | E13: =Cash_Flow!F6+Cash_Flow!F7-Cash_Flow!F8-Cash_Flow!F11 -> 2320.4784 | F13: =Cash_Flow!G6+Cash_Flow!G7-Cash_Flow!G8-Cash_Flow!G11 -> 2673.3696
A14: Discount Factor | B14: =1/(1+$B$5)^1 -> 0.87624549 | C14: =1/(1+$B$5)^2 -> 0.76780615 | D14: =1/(1+$B$5)^3 -> 0.67278667 | E14: =1/(1+$B$5)^4 -> 0.58952629 | F14: =1/(1+$B$5)^5 -> 0.51656975
A15: PV of FCFF | B15: =B13*B14 -> 730.93937 | C15: =C13*C14 -> 1181.6301 | D15: =D13*D14 -> 1352.3042 | E15: =E13*E14 -> 1367.983 | F15: =F13*F14 -> 1380.9818
A16: Sum of PV | B16: =NPV(WACC!F17,DCF_Valuation!B13:F13) -> 6013.8386
A19: Terminal Value Block | H19: Sanity Check Box
A20: Terminal g | B20: =B6 -> 0.035 | H20: Terminal Value % of EV | I20: =B22/I5 -> 1.3378594
A21: Terminal FCFF | B21: =F13*(1+'Control Panel'!B19) -> 2766.9375 | H21: Discounting check | I21: =B16-SUM(B15:F15) -> 0
A22: Terminal Value | B22: =B21/(WACC!F17-'Control Panel'!B19) -> 26046.006 | H22: EV Rebuilt Check | I22: =I5-(B16+B23) -> 0
A23: PV of Terminal Value | B23: =B22/(1+WACC!F17)^5 -> 13454.579

Sheet LBO_Sources_Uses
A1: LBO Entry - Sources & Uses
A2: All figures in Rs Cr unless stated
A4: Uses
A5: Entry EV | C5: ='Control Panel'!B28 -> 46367.08
A6: Plus: Transaction Fees (%) | C6: ='Control Panel'!B33*LBO_Sources_Uses!C5 -> 927.3416
A7: Plus: Refinancing Existing Debt | C7: =Balance_Sheet!B18 -> 7005
A8: Total Uses | C8: =C5+C6+C7 -> 54299.422
A10: Sources
A11: New Debt Raised | C11: ='Control Panel'!B23*LBO_Sources_Uses!C5 -> 23183.54
A12: Sponsor Equity Invested (Plug) | C12: =C8-C11 -> 31115.882
A13: Total Sources | C13: =C11+C12 -> 54299.422
A15: Sources - Uses Check | C15: =C13-C8 -> 0

Sheet Equity_Returns
A1: LBO Equity Returns & Exit Analysis
A2: All figures in Rs Cr unless stated
A4: Entry | F4: Deal Snapshot
A5: Entry EV | C5: ='Control Panel'!B28 -> 46367.08 | F5: Entry EV | H5: =C5 -> 46367.08
A6: Entry Net Debt | C6: =LBO_Sources_Uses!C11 -> 23183.54 | F6: Entry Equity | H6: =C7 -> 31115.882
A7: Entry Equity Invested | C7: =LBO_Sources_Uses!C12 -> 31115.882 | F7: Exit EV | H7: =C12 -> 142555.86
F8: Exit Equity | H8: =C14 -> 142555.86
A9: Exit | F9: MOIC | H9: =C18 -> 4.5814501
A10: Exit EV/EBITDA Multiple | C10: ='Control Panel'!B21 -> 24.95 | F10: IRR | H10: =C19 -> 0.66086495
A11: Exit EBITDA | C11: =Income_Statement!G8 -> 5713.6617
A12: Exit EV | C12: =C10*C11 -> 142555.86
A13: Less: Net Debt at Exit | C13: {=INDEX(LBO_Debt_Schedule!B11:G11,1,IRR_Sensitivity!J7+1)} -> 0
A14: Exit Equity Value | C14: =C12-C13 -> 142555.86
A16: Returns
A17: Holding Period (Years) | C17: =IRR_Sensitivity!J7 -> 3
A18: MOIC (x) | C18: =C14/C7 -> 4.5814501
A19: Equity IRR | C19: =C18^(1/C17)-1 -> 0.66086495

Sheet LBO_Debt_Schedule
A1: LBO Debt Schedule
A2: All figures in Rs Cr unless stated
A4: Particulars | B4: Entry (FY2025) | C4: FY2026E | D4: FY2027E | E4: FY2028E | F4: FY2029E | G4: FY2030E
A5: Opening Debt | B5: =LBO_Sources_Uses!C11 -> 23183.54 | C5: =B11 -> 16929.078 | D5: =C11 -> 8705.5239 | E5: =D11 -> 0 | F5: =E11 -> 0 | G5: =F11 -> 0
A6: New Borrowings | B6: 0 | C6: 0 | D6: 0 | E6: 0 | F6: 0 | G6: 0
A7: Interest Rate | B7: ='Control Panel'!$B$13 -> 0.11 | C7: ='Control Panel'!$B$13 -> 0.11 | D7: ='Control Panel'!$B$13 -> 0.11 | E7: ='Control Panel'!$B$13 -> 0.11 | F7: ='Control Panel'!$B$13 -> 0.11 | G7: ='Control Panel'!$B$13 -> 0.11
A8: Interest Expense | B8: 0 | C8: =C7*AVERAGE(C5,C11) -> 1409.9031 | D8: =D7*AVERAGE(D5,D11) -> 478.80381 | E8: =E7*AVERAGE(E5,E11) -> 0 | F8: =F7*AVERAGE(F5,F11) -> 0 | G8: =G7*AVERAGE(G5,G11) -> 0
A9: Cash Available for Repayment | B9: =Cash_Flow!B19 -> 6254.4617 | C9: =Cash_Flow!C19 -> 8223.5544 | D9: =Cash_Flow!D19 -> 11604.241 | E9: =Cash_Flow!E19 -> 15753.4 | F9: =Cash_Flow!F19 -> 20494.332 | G9: =Cash_Flow!G19 -> 25954.853
A10: Debt Payment | B10: =MIN(B9,B5+B6) -> 6254.4617 | C10: =MIN(C9,C5+C6) -> 8223.5544 | D10: =MIN(D9,D5+D6) -> 8705.5239 | E10: =MIN(E9,E5+E6) -> 0 | F10: =MIN(F9,F5+F6) -> 0 | G10: =MIN(G9,G5+G6) -> 0
A11: Closing Debt | B11: =B5+B6-B10 -> 16929.078 | C11: =C5+C6-C10 -> 8705.5239 | D11: =D5+D6-D10 -> 0 | E11: =E5+E6-E10 -> 0 | F11: =F5+F6-F10 -> 0 | G11: =G5+G6-G10 -> 0

Sheet Exit_Comparison
A1: DCF vs LBO Exit Comparison
A2: All figures in Rs Cr unless stated
A4: DCF Valuation
A5: Intrinsic EV (DCF) | C5: =DCF_Valuation!I5 -> 19468.417
A6: DCF Equity Value | C6: =DCF_Valuation!I7 -> 18717.879
A7: DCF Value / Share | C7: =DCF_Valuation!I9 -> 558.67295
A9: LBO Exit
A10: Exit EV (from multiple) | C10: =Equity_Returns!H7 -> 142555.86
A11: Exit Equity Value | C11: =Equity_Returns!C14 -> 142555.86
A12: Exit EV/EBITDA Multiple | C12: =Equity_Returns!C10 -> 24.95
A14: Comparison
A15: Entry EV | C15: ='Control Panel'!B28 -> 46367.08
A16: Premium / (Discount) to DCF EV | C16: =C15/C5-1 -> 1.3816564
A17: Exit EV vs DCF EV | C17: =C10/C5-1 -> 6.3224165
A20: Interpretation
A21: Compares entry and exit valuation against intrinsic DCF value to assess whether returns are driven by buying below intrinsic value, leverage, operational improvement, or exit multiple expansion.

Sheet IRR_Sensitivity
A1: Equity IRR Sensitivity - Exit Multiple vs Holding Period
A4: =Equity_Returns!C19 -> 0.66086495 | B4: 3 | C4: 4 | D4: 5
A5: 8 | B5: 0.136774 | C5: 0.10091959 | D5: 0.079952067
A6: 9 | B6: 0.18229261 | C6: 0.133819 | D6: 0.10569408 | I6: Exit EV/EBITDA | J6: 24.95
A7: 10 | B7: 0.22455267 | C7: 0.16408074 | D7: 0.1292406 | I7: Holding Period | J7: =CHOOSE(MATCH('Control Panel'!B4,{"Base","Upside","Downside"},0),'Scenario Assumptions'!B24,'Scenario Assumptions'!C24,'Scenario Assumptions'!D24) -> 3

Sheet LBO_Dashboard
A1: LBO Transaction Summary Dashboard
A2: Aurex Research | Akshat Gupta
A4: Key Assumptions | M4: Supporting Visuals
A6: Entry Snapshot | D6: Exit Snapshot | G6: Returns | J6: Key Assumptions
A7: Entry EV | B7: ='Control Panel'!B28 -> 46367.08 | D7: Exit EV/EBITDA | E7: ='Control Panel'!B21 -> 24.95 | G7: Holding Period (yrs) | H7: =Equity_Returns!C17 -> 3 | J7: Entry EV | K7: =B7 -> 46367.08
A8: Entry EV/EBITDA | B8: ='Control Panel'!B20 -> 24.95 | D8: Exit EBITDA | E8: =Equity_Returns!C11 -> 5713.6617 | G8: MOIC | H8: =Equity_Returns!C18 -> 4.5814501 | J8: Target Debt % | K8: ='Control Panel'!B23 -> 0.5
A9: Entry EBITDA | B9: =Income_Statement!B8 -> 2078.7458 | D9: Exit EV | E9: =Equity_Returns!H7 -> 142555.86 | G9: Equity IRR | H9: =Equity_Returns!C19 -> 0.66086495 | J9: Exit Multiple | K9: ='Control Panel'!B21 -> 24.95
A10: New Debt Raised | B10: =LBO_Sources_Uses!C11 -> 23183.54 | D10: Exit Net Debt | E10: =Equity_Returns!C13 -> 0 | J10: Holding Period | K10: =H7 -> 3
A11: Equity Invested | B11: =LBO_Sources_Uses!C12 -> 31115.882 | D11: Exit Equity Value | E11: =Equity_Returns!C14 -> 142555.86 | J11: Cost of Debt | K11: ='Control Panel'!B13 -> 0.11
A12: Debt/EV | B12: =B10/B7 -> 0.5 | J12: Fees % | K12: ='Control Panel'!B33 -> 0.02
A15: Main Visuals

Sheet Helper Table
A1: Equity Bridge | B1: Value | G1: Debt Paydown | P1: Funding Mix Chart | X1: EBITDA Trend Growth
A2: Entry Equity Value | B2: =Equity_Returns!H6 -> 31115.882 | G2: Year | H2: FY2026E | I2: FY2027E | J2: FY2028E | K2: FY2029E | L2: FY2030E | P2: Source | Q2: Amount | X2: Year | Y2: FY2026E | Z2: FY2027E | AA2: FY2028E | AB2: FY2029E | AC2: FY2030E
A3: Deleveraging (Debt Paydown) | B3: =Equity_Returns!C6-Equity_Returns!C13 -> 23183.54 | G3: Debt Balance | H3: =LBO_Debt_Schedule!C11 -> 8705.5239 | I3: =LBO_Debt_Schedule!D11 -> 0 | J3: =LBO_Debt_Schedule!E11 -> 0 | K3: =LBO_Debt_Schedule!F11 -> 0 | L3: =LBO_Debt_Schedule!G11 -> 0 | P3: Debt | Q3: =LBO_Sources_Uses!C11 -> 23183.54 | X3: EBITDA | Y3: =Income_Statement!C8 -> 2774.3573
A4: Operational Value Creation | B4: =Equity_Returns!H8-Equity_Returns!H6-(Equity_Returns!C6-Equity_Returns!C13) -> 88256.438 | G4: EBITDA | H4: =Income_Statement!C8 -> 2774.3573 | I4: =Income_Statement!D8 -> 3545.3056 | J4: =Income_Statement!E8 -> 4331.788 | K4: =Income_Statement!F8 -> 4901.4181 | L4: =Income_Statement!G8 -> 5713.6617 | P4: Equity | Q4: =LBO_Sources_Uses!C12 -> 31115.882
A5: Exit Equity Value | B5: =Equity_Returns!H8 -> 142555.86 | G5: Debt/EBITDA | H5: =IFERROR(H3/H4,0) -> 3.1378524 | I5: =IFERROR(I3/I4,0) -> 0 | J5: =IFERROR(J3/J4,0) -> 0 | K5: =IFERROR(K3/K4,0) -> 0 | L5: =IFERROR(L3/L4,0) -> 0 | P5: Total | Q5: =SUM(Q3:Q4) -> 54299.422
